Workbook

Sheet Sources
A1: CoreWeave, Inc. (CRWV, CIK 0001769628) - Source Filings
A2: R1 output. Raw tabs contain ONLY tables copied from these documents. Units: $ in millions unless the tab header says otherwise.
A3: ANALYSIS DATE: August 13, 2026. Use only information public on or before that date. Financials as of June 30, 2026 (Q2 2026 10-Q); capitalization pro forma for subsequent events disclosed by then (DDTL 5.5 facility, Aug 2026 revolver draw). Exclude anything later (e.g., Sep 2026 convertible notes, Q3 results).
A4: # | B4: Document | C4: Form | D4: Filed | E4: Period covered | F4: Accession no. | G4: Used for | H4: Raw tabs | I4: Link
A5: 1 | B5: Quarterly report Q2 2026 | C5: 10-Q | D5: 2026-08-12 | E5: Quarter / 6M ended 2026-06-30 | F5: 0001769628-26-000366 | G5: Latest GAAP statements; Note 10 debt tables + MD&A liquidity (R4); debt note text (R5) | H5: 10Q_BS, 10Q_IS, 10Q_CF, 10Q_Debt, 10Q_DebtText | I5: https://www.sec.gov/Archives/edgar/data/1769628/000176962826000366/crwv-20260630.htm
A6: 2 | B6: Annual report FY2025 | C6: 10-K | D6: 2026-03-02 | E6: Year ended 2025-12-31 | F6: 0001769628-26-000104 | G6: Full-year GAAP statements (for LTM = FY25 + 6M26 - 6M25); full business description; full debt note | H6: 10K_BS, 10K_IS, 10K_CF, 10K_DebtText | I6: https://www.sec.gov/Archives/edgar/data/1769628/000176962826000104/0001769628-26-000104-index.htm
A7: 3 | B7: Q2 2026 earnings press release | C7: 8-K Item 2.02, Ex.99.1 | D7: 2026-08-11 | E7: Quarter / 6M ended 2026-06-30 | F7: 0001769628-26-000362 | G7: Non-GAAP reconciliations (Adj. EBITDA etc.) - not in the 10-Q | H7: PR_Q2-26 | I7: https://www.sec.gov/Archives/edgar/data/1769628/000176962826000362/coreweave2q26earningspress.htm
A8: 4 | B8: Q4 2025 earnings press release | C8: 8-K Item 2.02, Ex.99.1 | D8: 2026-02-26 | E8: Quarter / year ended 2025-12-31 | F8: 0001769628-26-000094 | G8: FY2025 non-GAAP reconciliations (for LTM Adj. EBITDA) | H8: PR_Q4-25 | I8: https://www.sec.gov/Archives/edgar/data/1769628/000176962826000094/coreweave4q25earningspress.htm
A9: 5 | B9: DDTL 5.5 facility closing | C9: 8-K Items 1.01, 2.03, 7.01; Ex.10.2, Ex.99.1 | D9: 2026-08-10 | E9: Event date 2026-08-07 | F9: 0001769628-26-000357 | G9: Subsequent event: new $2.6bn facility (with 10-Q Note 16) - pro forma capitalization at 2026-08-13 | H9: Subsequent | I9: https://www.sec.gov/Archives/edgar/data/1769628/000176962826000357/0001769628-26-000357-index.htm
A10: 6 | B10: Q3 and FY 2026 Outlook Presentation | C10: IR website PDF (not an SEC filing) | D10: 2026-08-11 | E10: Guidance for Q3'26 and FY'26 | F10: n/a | G10: Company guidance: revenue, adj. operating income, interest expense, capex, exit ARR (Funding Need) | H10: Guidance (A) | I10: https://s205.q4cdn.com/133937190/files/doc_financials/2026/q2/CoreWeave-Q2-26-Earnings-Outlook-Presentation.pdf
A11: 7 | B11: Q2'26 Earnings Presentation | C11: IR website PDF (not an SEC filing) | D11: 2026-08-11 | E11: Quarter / 6M ended 2026-06-30 | F11: n/a | G11: Company definition of capex and its calculation (gross PP&E increase less change in CIP) - the basis of the capex guidance | H11: Guidance (B) | I11: https://s205.q4cdn.com/133937190/files/doc_financials/2026/q2/CoreWeave-Q2-26-Earnings-Presentation.pdf
A12: 8 | B12: Q2 2026 earnings call transcript | C12: IR website PDF (FactSet corrected transcript) | D12: 2026-08-11 (call date) | E12: Quarter ended 2026-06-30 | F12: n/a | G12: CFO remarks on capex, liquidity, guidance; contracted power and 2030 target | H12: Guidance (C) | I12: https://s205.q4cdn.com/133937190/files/doc_financials/2026/q2/CRWV-US-CORRECTED-TRANSCRIPT-CoreWeave-Q2-2026-Earnings-Call-11August2026.pdf
A14: Progress
A15: R1-R3 done: this list, 10Q_* and 10K_* statements, PR_* non-GAAP tables. R4 done: 10Q_Debt (Note 10 tables from R32 + MD&A liquidity table).
A16: R5 done: 10Q_DebtText (Q2 10-Q Note 10 full text, R16) and 10K_DebtText (FY25 10-K Note 10 full text, R18 - terms of older debt the 10-Q does not repeat).
A17: R6 done: Subsequent (10-Q Note 16 + DDTL 5.5 8-K body, press release, parent guarantee s.2.1). Sep 2026 convertible notes excluded (after analysis date). Raw is complete.
A18: R7 done (added after Step 1, for Step 2 Funding Need): Guidance - Outlook Presentation slide 3, Earnings Presentation capex definition and calculation (slides 8, 14, 16), CFO guidance remarks from the call transcript. Company material, not SEC filings.
A20: How these were found on EDGAR
A21: 1. sec.gov > EDGAR full-text / company search > 'CoreWeave' > company page (CIK 0001769628).
A22: 2. Filter Filing Type = 10-Q / 10-K: take the latest of each. Filter = 8-K: earnings releases are the 8-Ks with Item 2.02 (Results of Operations).
A23: 3. Open a filing's index page > 'Interactive Data' (R pages): each statement is its own page (R2 = balance sheet, R4 = income statement, R6 = cash flow in this 10-Q). Financial_Report.xlsx on the same page has all of them in Excel.
A24: 4. Press releases have no R pages: open Ex.99.1 and copy the reconciliation tables at the end.
A26: Copy rules used (what was and was NOT changed)
A27: Kept exactly: every row label, row order, column headers, footnote markers [1], section/abstract rows, units shown in each table title.
... A31: Verification: the copied text of all 6 GAAP tables and 6 press-release tables was fingerprinted (SHA-256) against the SEC pages and matched exactly.

Sheet 10Q_BS
A1: 10-Q Q2 2026 - Condensed Consolidated Balance Sheets
A2: Source: 10-Q filed 2026-08-12, R2.htm
A3: https://www.sec.gov/Archives/edgar/data/1769628/000176962826000366/R2.htm
A4: Copied as shown on the SEC R page.
A6: CONDENSED CONSOLIDATED BALANCE SHEETS - USD ($) $ in Millions | B6: Jun. 30, 2026 | C6: Dec. 31, 2025
A7: Current assets
A8: Cash and cash equivalents | B8: 5524 | C8: 3127
A9: Restricted cash and cash equivalents, current | B9: 873 | C9: 819
A10: Marketable securities | B10: 15 | C10: 34
A11: Accounts receivable, net | B11: 2541 | C11: 3169
A12: Prepaid expenses and other current assets | B12: 567 | C12: 339
A13: Total current assets | B13: 9520 | C13: 7488
A14: Restricted cash and cash equivalents, non-current | B14: 507 | C14: 184
A15: Property and equipment, net | B15: 46736 | C15: 30557
A16: Operating lease right-of-use assets | B16: 16595 | C16: 8231
A17: Intangible assets, net | B17: 245 | C17: 235
A18: Goodwill | B18: 1101 | C18: 1101
A19: Other non-current assets | B19: 2366 | C19: 1506
A20: Total assets | B20: 77070 | C20: 49302
A21: Current liabilities
A22: Accounts payable | B22: 3633 | C22: 1623
A23: Accrued liabilities | B23: 6424 | C23: 5773
A24: Recourse debt, current | B24: 6235 | C24: 6118
A25: Non-recourse debt, current | B25: 1278 | C25: 590
A26: Deferred revenue, current | B26: 2686 | C26: 1709
A27: Operating lease liabilities, current | B27: 584 | C27: 427
A28: Finance lease liabilities, current | B28: 7 | C28: 38
A29: Other current liabilities | B29: 70 | C29: 162
A30: Total current liabilities | B30: 20917 | C30: 16440
A31: Recourse debt, non-current | B31: 25170 | C31: 14608
A32: Non-recourse debt, non-current | B32: 2385 | C32: 57
A33: Deferred revenue, non-current | B33: 7006 | C33: 6476
... A38: Total liabilities | B38: 72046 | C38: 45967
A39: Commitments and contingencies (Note 9)
A40: Stockholders' equity
A41: Preferred stock | B41: 0 | C41: 0
A42: Treasury stock, at cost | B42: -34 | C42: -34
A43: Additional paid-in capital | B43: 9085 | C43: 6012
A44: Accumulated other comprehensive loss | B44: -18 | C44: 0
A45: Accumulated deficit | B45: -4009 | C45: -2643
A46: Total stockholders' equity | B46: 5024 | C46: 3335
A47: Total liabilities and stockholders' equity | B47: 77070 | C47: 49302
A48: Common Class A
A49: Stockholders' equity
A50: Common stock | B50: 0 | C50: 0
A51: Common Class B
A52: Stockholders' equity
A53: Common stock | B53: 0 | C53: 0
A54: Common Class C
A55: Stockholders' equity
A56: Common stock | B56: 0 | C56: 0
A58: Checks (added by us, NOT part of the SEC table) - all should be 0
A59: Current assets | B59: =SUM(B8:B12)-B13 | C59: =SUM(C8:C12)-C13
A60: Total assets | B60: =B13+SUM(B14:B19)-B20 | C60: =C13+SUM(C14:C19)-C20
A61: Current liabilities | B61: =SUM(B22:B29)-B30 | C61: =SUM(C22:C29)-C30
A62: Total liabilities | B62: =B30+SUM(B31:B37)-B38 | C62: =C30+SUM(C31:C37)-C38
A63: Stockholders' equity | B63: =SUM(B41:B45)-B46 | C63: =SUM(C41:C45)-C46
A64: Assets = liabilities + equity | B64: =B20-B38-B46 | C64: =C20-C38-C46

Sheet 10Q_IS
A1: 10-Q Q2 2026 - Condensed Consolidated Statements of Operations
A2: Source: 10-Q filed 2026-08-12, R4.htm
A3: https://www.sec.gov/Archives/edgar/data/1769628/000176962826000366/R4.htm
A4: Copied as shown on the SEC R page.
A6: CONDENSED CONSOLIDATED STATEMENTS OF OPERATIONS AND COMPREHENSIVE LOSS - USD ($) shares in Millions, $ in Millions | B6: 3 Months Ended | D6: 6 Months Ended
B7: Jun. 30, 2026 | C7: Jun. 30, 2025 | D7: Jun. 30, 2026 | E7: Jun. 30, 2025
A8: Income Statement [Abstract]
A9: Revenue | B9: 2575 | C9: 1212 | D9: 4653 | E9: 2194
A10: Operating expenses:
A11: Cost of revenue | B11: 879 | C11: 313 | D11: 1595 | E11: 575
A12: Technology and infrastructure | B12: 1507 | C12: 670 | D12: 2780 | E12: 1231
A13: Sales and marketing | B13: 60 | C13: 36 | D13: 129 | E13: 47
A14: General and administrative | B14: 178 | C14: 174 | D14: 342 | E14: 349
A15: Total operating expenses | B15: 2624 | C15: 1193 | D15: 4846 | E15: 2202
A16: Operating income (loss) | B16: -49 | C16: 19 | D16: -193 | E16: -8
A17: Gain (loss) on fair value adjustments | B17: 0 | C17: 0 | D17: 0 | E17: 27
A18: Interest expense, net | B18: -640 | C18: -267 | D18: -1176 | E18: -531
A19: Other income (expense), net | B19: 125 | C19: 6 | D19: 149 | E19: 1
A20: Loss before income taxes | B20: -564 | C20: -242 | D20: -1220 | E20: -511
A21: Provision for income taxes | B21: 62 | C21: 48 | D21: 146 | E21: 94
A22: Net loss | B22: -626 | C22: -290 | D22: -1366 | E22: -605
... A30: Weighted-average shares used in computing net loss per share attributable to common stockholders, diluted (in shares) | B30: 551 | C30: 487 | D30: 539 | E30: 369
A32: Checks (added by us, NOT part of the SEC table) - all should be 0
A33: Total operating expenses | B33: =SUM(B11:B14)-B15 | C33: =SUM(C11:C14)-C15 | D33: =SUM(D11:D14)-D15 | E33: =SUM(E11:E14)-E15
A34: Operating income | B34: =B9-B15-B16 | C34: =C9-C15-C16 | D34: =D9-D15-D16 | E34: =E9-E15-E16
A35: Loss before income taxes | B35: =SUM(B16:B19)-B20 | C35: =SUM(C16:C19)-C20 | D35: =SUM(D16:D19)-D20 | E35: =SUM(E16:E19)-E20
A36: Net loss | B36: =B20-B21-B22 | C36: =C20-C21-C22 | D36: =D20-D21-D22 | E36: =E20-E21-E22
A37: Total comprehensive loss | B37: =B22+B23-B24 | C37: =C22+C23-C24 | D37: =D22+D23-D24 | E37: =E22+E23-E24

Sheet 10Q_CF
A1: 10-Q Q2 2026 - Condensed Consolidated Statements of Cash Flows
A2: Source: 10-Q filed 2026-08-12, R6.htm
A3: https://www.sec.gov/Archives/edgar/data/1769628/000176962826000366/R6.htm
A4: NOTE: this R page is labelled '$ in Thousands' (1,366,000 = $1,366 million). The 10-Q document itself shows $ in millions. Copied as shown.
A6: CONDENSED CONSOLIDATED STATEMENTS OF CASH FLOWS - USD ($) $ in Thousands | B6: 6 Months Ended
B7: Jun. 30, 2026 | C7: Jun. 30, 2025
A8: Cash flows from operating activities:
A9: Net loss | B9: -1366000 | C9: -605000
A10: Adjustments to reconcile net loss to net cash provided by operating activities
A11: Depreciation and amortization | B11: 2540000 | C11: 1003000
A12: Amortization of debt discounts and issuance costs and accretion of redemption premiums | B12: 86000 | C12: 67000
A13: Stock-based compensation expense | B13: 318000 | C13: 329000
A14: Non-cash lease expense | B14: 365000 | C14: 144000
A15: Deferred income taxes | B15: 140000 | C15: 91000
A16: Gain on fair value adjustments | B16: 0 | C16: -27000
A17: Other non-cash reconciling items | B17: 97000 | C17: 39000
A18: Changes in operating assets and liabilities, net of effect of business acquisitions:
A19: Accounts receivable | B19: 607000 | C19: -1505000
A20: Prepaid expenses and other assets | B20: -611000 | C20: -70000
A21: Accounts payable and accrued expenses | B21: 304000 | C21: -289000
A22: Deferred revenue | B22: 1365000 | C22: 743000
A23: Lease liabilities | B23: -182000 | C23: -110000
A24: Net cash provided by (used in) operating activities | B24: 3663000 | C24: -190000
A25: Cash flows from investing activities:
A26: Purchase of property and equipment, including capitalized internal-use software | B26: -14117000 | C26: -3860000
A27: Maturities and sales of marketable securities | B27: 18000 | C27: 29000
A28: Investments related to joint ventures | B28: -550000 | C28: -32000
A29: Purchase of strategic investments | B29: -138000 | C29: 0
A30: Sales of warrants received as lease incentive | B30: 0 | C30: 101000
A31: Issuance of notes receivable | B31: 0 | C31: -73000
A32: Business combination, net of cash acquired | B32: 0 | C32: -46000
A33: Other investing activities | B33: -87000 | C33: 6000
A34: Net cash used in investing activities | B34: -14874000 | C34: -3875000
A35: Cash flows from financing activities:
A36: Proceeds from issuance of debt, net | B36: 16747000 | C36: 4396000
A37: Repayments of debt | B37: -5219000 | C37: -1575000
A38: Purchase of capped calls related to convertible senior notes | B38: -492000 | C38: 0
A39: Issuance of common stock in private placements, net of issuance costs | B39: 2982000 | C39: 0
A40: Payment of tax withholdings on settlement of restricted stock units | B40: 0 | C40: -133000
A41: Proceeds from initial public offering, net of underwriting discounts and commissions | B41: 0 | C41: 1491000
A42: Redeemable convertible preferred stock cash dividends paid | B42: 0 | C42: -29000
A43: Other financing activities | B43: -33000 | C43: -66000
A44: Net cash provided by financing activities | B44: 13985000 | C44: 4084000
A45: Net increase (decrease) in cash, cash equivalents, and restricted cash | B45: 2774000 | C45: 19000
A46: Cash, cash equivalents, and restricted cash—beginning of period | B46: 4130000 | C46: 2035000
A47: Cash, cash equivalents, and restricted cash—end of period | B47: 6904000 | C47: 2054000
A48: Supplemental disclosures of cash flow information:
A49: Cash paid for interest, net of capitalized amounts | B49: 806000 | C49: 362000
A50: Non-cash investing and financing activities:
A51: Liabilities related to property and equipment additions, including OEM financed additions | B51: 9796000 | C51: 2155000
A52: Reclassification of liabilities related to property and equipment additions to debt upon execution of OEM financing arrangements | B52: 1469000 | C52: 0
A53: Operating lease right-of-use assets acquired through lease liability | B53: 8359000 | C53: 969000
A54: Conversion of convertible promissory notes | B54: 195000 | C54: 0
A55: Conversion of redeemable convertible preferred stock in connection with initial public offering | B55: 0 | C55: 1722000
A56: Issuance of common stock, restricted stock units, and restricted stock awards for business combinations | B56: 0 | C56: 933000
A57: Issuance of common stock for contract incentive | B57: 0 | C57: 350000
A58: Reclassification of warrant liabilities to equity | B58: 0 | C58: 173000
A59: Reclassification of customer deposit to debt | B59: 0 | C59: 230000
A60: Warrants received as lease incentive | B60: 0 | C60: 90000
A61: Non-cash investments | B61: 0 | C61: 72000
A62: Reconciliation of cash, cash equivalents, and restricted cash to condensed consolidated balance sheets:
A63: Cash and cash equivalents | B63: 5524000 | C63: 1153000
A64: Restricted cash and cash equivalents, current | B64: 873000 | C64: 560000
A65: Restricted cash and cash equivalents, non-current | B65: 507000 | C65: 341000
A66: Total cash, cash equivalents, and restricted cash | B66: 6904000 | C66: 2054000
A68: Checks (added by us, NOT part of the SEC table) - all should be 0
A69: Operating activities | B69: =SUM(B9:B23)-B24 | C69: =SUM(C9:C23)-C24
A70: Investing activities | B70: =SUM(B26:B33)-B34 | C70: =SUM(C26:C33)-C34
A71: Financing activities | B71: =SUM(B36:B43)-B44 | C71: =SUM(C36:C43)-C44
A72: Net change in cash | B72: =B24+B34+B44-B45 | C72: =C24+C34+C44-C45
A73: Cash roll-forward | B73: =B46+B45-B47 | C73: =C46+C45-C47
A74: Cash reconciliation | B74: =SUM(B63:B65)-B66 | C74: =SUM(C63:C65)-C66

Sheet 10Q_Debt
A1: 10-Q Q2 2026 - Note 10 Debt tables + MD&A liquidity table
A2: Source: 10-Q filed 2026-08-12. Tables 1-4 from R32.htm 'Debt (Tables)'; table 5 from the 10-Q document, Item 2 MD&A, Liquidity and Capital Resources
A3: https://www.sec.gov/Archives/edgar/data/1769628/000176962826000366/R32.htm
A4: Copied as shown ($ in millions). Rates like '15%' stored as 0.15; '—' stored as 0. Footnotes copied word for word below each table.
A6: Table 1. The total debt obligations are as follows (dollars in millions)
B7: Maturities | C7: EffectiveInterestRates | D7: June 30,2026 | E7: December 31,2025
A8: Recourse debt:
A9: DDTL 1.0 Facility | B9: Mar 2028 | C9: 0.15 | D9: 1300 | E9: 1553
A10: DDTL 2.0 Facility | B10: Aug 2030 | C10: 0.11 | D10: 3190 | E10: 5037
A11: DDTL 2.1 Facility | B11: Mar 2031 | C11: 0.09 | D11: 3000 | E11: 2741
A12: DDTL 3.0 Facility | B12: Aug 2030 | C12: 0.09 | D12: 2215 | E12: 340
A13: DDTL 5.0 Facility | B13: Nov 2031 | C13: 0.09 | D13: 1101 | E13: 0
A14: 2030 Senior Notes | B14: Jun 2030 | C14: 0.1 | D14: 2000 | E14: 2000
A15: 2031 9.00% Senior Notes | B15: Feb 2031 | C15: 0.1 | D15: 1750 | E15: 1750
A16: 2031 9.75% Senior Notes | B16: Oct 2031 | C16: 0.1 | D16: 2750 | E16: 0
A17: 2032 9.625% Senior Notes | B17: Jul 2032 | C17: 0.1 | D17: 1250 | E17: 0
A18: 2032 EUR Senior Notes(1) | B18: Jul 2032 | C18: 0.09 | D18: 2279 | E18: 0
A19: 2031 Convertible Senior Notes | B19: Dec 2031 | C19: 0.02 | D19: 2588 | E19: 2588
A20: 2032 Convertible Senior Notes | B20: Oct 2032 | C20: 0.02 | D20: 4000 | E20: 0
... A24: Magnetar Loan | B24: Jan 2029 | C24: 0.12 | D24: 189 | E24: 273
A25: Less: Unamortized discount and issuance costs | D25: -427 | E25: -242
A26: Total recourse debt, net of unamortized discount and issuance costs | D26: 31405 | E26: 20726
A27: Less: Recourse debt, current | D27: -6235 | E27: -6118
A28: Total recourse debt, non-current | D28: 25170 | E28: 14608
A29: Non-recourse debt:
A30: DDTL 4.0 Facility | B30: Mar 2032 | C30: 0.07 | D30: 2837 | E30: 0
A31: OEM and Software License Financing Arrangements | B31: Aug 2026 - Aug 2028 | C31: 0.09 | D31: 882 | E31: 647
A32: Less: Unamortized discount and issuance costs | D32: -56 | E32: 0
A33: Total non-recourse debt, net of unamortized discount and issuance costs | D33: 3663 | E33: 647
A34: Less: Non-recourse debt, current | D34: -1278 | E34: -590
A35: Total non-recourse debt, non-current | D35: 2385 | E35: 57
A36: (1) In June 2026, the Company entered into cross currency interest rate swaps designated as a fair value hedge, to hedge changes in the fair value on the 2032 EUR Senior Notes, attributable to changes in foreign currency exchange rate.
A38: Table 2. During the six months ended June 30, 2026, the Company entered into DDTL facilities and issued senior notes as follows (dollars in millions)
B39: Date of Issuance | C39: Stated Interest Rates(1) | D39: Amount(2)
A40: DDTL 4.0 Facility | B40: March 2026 | C40: SOFR + 2.25%; Treasury + 2.00% | D40: 8500
A41: DDTL 5.0 Facility | B41: May 2026 | C41: SOFR + 4.50% | D41: 3100
A42: 2031 9.75% Senior Notes | B42: April 2026 | C42: 9.75% | D42: 2750
A43: 2032 9.625% Senior Notes | B43: June 2026 | C43: 9.625% | D43: 1250
A44: 2032 EUR Senior Notes | B44: June 2026 | C44: 8.50% | D44: 2000 | E44: € (source shows € 2,000)
A45: 2032 Convertible Senior Notes | B45: April 2026 | C45: 1.75% | D45: 4000
A46: (1) DDTL Facility floating-rate commitments are subject to an interest rate per annum equal to, at the Company's option, either the SOFR or the alternative base rate plus a spread. For the DDTL 4.0 Facility, refer to the Delayed Draw Term Loans below for further details on interest rates.
A47: (2) Amounts represent borrowing capacity for the DDTL Facilities and the principal amounts for the Senior Notes.
A49: Table 3. As of June 30, 2026, the future principal payments for the Company's total debt were as follows (in millions)
A50: Years Ending December 31, | B50: Amount
A51: Remaining portion of 2026 | B51: 4413
A52: 2027 | B52: 6184
A53: 2028 | B53: 4416
A54: 2029 | B54: 2421
A55: 2030 | B55: 3221
A56: Thereafter | B56: 14896
A57: Total | B57: 35551
A59: Table 4. The total interest expense for the Company's debt obligations was as follows (in millions)
B60: Three Months Ended June 30, | D60: Six Months Ended June 30,
B61: 2026 | C61: 2025 | D61: 2026 | E61: 2025
A62: Contractual interest expense | B62: 592 | C62: 250 | D62: 1075 | E62: 483
A63: Amortization of debt discounts and issuance costs and accretion of redemption premiums | B63: 45 | C63: 29 | D63: 86 | E63: 67
A64: Less: capitalized interest | B64: -79 | C64: -23 | D64: -176 | E64: -36
A65: Total | B65: 558 | C65: 256 | D65: 985 | E65: 514
A67: Table 5. MD&A - Liquidity and Capital Resources (in millions)
A68: Our operations have been financed primarily through net proceeds from sales of our equity securities, including in our IPO, and from borrowings pursuant to our Credit Facilities and the issuances of debt securities. The following table summarizes our principal sources of liquidity for the periods presented (in millions):
B69: June 30,2026 | C69: December 31,2025
A70: Cash and cash equivalents | B70: 5524 | C70: 3127
A71: Marketable securities | B71: 15 | C71: 34
A72: Availability under existing facilities(1) | B72: 10014 | C72: 3701
A73: Total liquidity | B73: 15553 | C73: 6862
A74: (1)Refers to secured commitments under the revolving credit facility and delayed draw term loan agreements.
A76: Checks (added by us, NOT part of the 10-Q) - all should be 0
A77: Recourse facilities - discount = total recourse (Jun / Dec) | D77: =SUM(D9:D25)-D26 | E77: =SUM(E9:E25)-E26
A78: Total recourse - current = non-current | D78: =D26+D27-D28 | E78: =E26+E27-E28
A79: Non-recourse facilities - discount = total non-recourse | D79: =SUM(D30:D32)-D33 | E79: =SUM(E30:E32)-E33
A80: Total non-recourse - current = non-current | D80: =D33+D34-D35 | E80: =E33+E34-E35
A81: Recourse current vs 10Q_BS | D81: =-D27-'10Q_BS'!B24 | E81: =-E27-'10Q_BS'!C24
A82: Recourse non-current vs 10Q_BS | D82: =D28-'10Q_BS'!B31 | E82: =E28-'10Q_BS'!C31
A83: Non-recourse current vs 10Q_BS | D83: =-D34-'10Q_BS'!B25 | E83: =-E34-'10Q_BS'!C25
A84: Non-recourse non-current vs 10Q_BS | D84: =D35-'10Q_BS'!B32 | E84: =E35-'10Q_BS'!C32
A85: Maturity schedule: years add up to Total | B85: =SUM(B51:B56)-B57
A86: Principal BEFORE discounts (Table 1, Jun) = maturity Total | B86: =SUM(D9:D24)+SUM(D30:D31)-B57
A87: Interest components add up to Total | B87: =SUM(B62:B64)-B65 | C87: =SUM(C62:C64)-C65 | D87: =SUM(D62:D64)-D65 | E87: =SUM(E62:E64)-E65
A88: Liquidity components add up to Total | B88: =SUM(B70:B72)-B73 | C88: =SUM(C70:C72)-C73
A89: Liquidity cash vs 10Q_BS cash | B89: =B70-'10Q_BS'!B8 | C89: =C70-'10Q_BS'!C8

Sheet 10Q_DebtText
A1: 10-Q Q2 2026 - Note 10 Debt (full text)
A2: Source: 10-Q filed 2026-08-12, R16.htm 'Debt'
A3: https://www.sec.gov/Archives/edgar/data/1769628/000176962826000366/R16.htm
A4: Full note text, word for word, one paragraph per row, in the original order. Column B repeats the nearest heading above (navigation only). Where SEC splits a paragraph across a page break it stays split. [TABLE] = a table in the note: the first four are copied as numbers in 10Q_Debt (Tables 1-4); the last one (DCSP financing obligation) is not copied.
A6: ¶ | B6: Section (heading in source) | C6: Text (verbatim)
A7: 1 | B7: (note intro) | C7: The total debt obligations are as follows (dollars in millions):
A8: 2 | B8: (note intro) | C8: (1) In June 2026, the Company entered into cross currency interest rate swaps designated as a fair value hedge, to hedge changes in the fair value on the 2032 EUR Senior Notes, attributable to changes in foreign currency exchange rate.
A9: 3 | B9: (note intro) | C9: [TABLE]
A10: 4 | B10: (note intro) | C10: As of June 30, 2026, the Company's weighted-average interest rate on short-term debt instruments related to certain of the OEM Financing Arrangements was 9%.
A11: 5 | B11: (note intro) | C11: Non-recourse debt represents debt facilities and financing arrangements entered into by certain of the Company’s subsidiaries for which recourse is limited to the assets of the applicable subsidiaries. CoreWeave, Inc., the ultimate parent company, is not otherwise liable for such debt, except in cases where the Company provides limited guarantees under which recourse may arise only upon specified events, such as actual fraud, willful misconduct, misappropriation of collateral, certain voluntary or consented bankruptcy actions, or other customary non-recourse carve-out obligations. These limited guarantees do not represent general guarantees of repayment of principal, interest or other ordinary debt service payments. Recourse debt represents debt facilities and financing arrangements that are either direct obligations of
A12: 6 | B12: (note intro) | C12: CoreWeave, Inc. or obligations of certain of the Company’s subsidiaries that are unconditionally and irrevocably guaranteed by CoreWeave, Inc.
A13: 7 | B13: (note intro) | C13: As of June 30, 2026, the future principal payments for the Company's total debt were as follows (in millions):
A14: 8 | B14: (note intro) | C14: [TABLE]
A15: 9 | B15: (note intro) | C15: The total interest expense for the Company's debt obligations was as follows (in millions):
A16: 10 | B16: (note intro) | C16: [TABLE]
A17: 11 | B17: (note intro) | C17: During the six months ended June 30, 2026, the Company entered into DDTL facilities and issued senior notes (each as defined in this Note 10—Debt) as follows (dollars in millions):
A18: 12 | B18: (note intro) | C18: [TABLE]
... A73: 67 | B73: DCSP Financing Arrangements | C73: During the three months ended June 30, 2026, the Company reassessed the DCSP as a VIE following changes affecting the adequacy of the DCSP's equity investment at risk. The Company concluded that it was not the primary beneficiary of the DCSP because it lacked the power to direct the activities that most significantly impact the DCSP's economic performance. Accordingly, the Company did not consolidate the DCSP. The Company's maximum exposure to loss related to the DCSP consists of the carrying amount of the DCSP Note Receivable and the Company's commitment to fund the remaining completion work at the data center. This funding commitment is not subject to a contractual cap; however, the Company estimates the remaining funding obligation to be not material. Amounts funded under this commitment are recoverable from the DCSP only through contingent, unsecured reimbursement rights.

Sheet 10K_BS
A1: 10-K FY2025 - Consolidated Balance Sheets
A2: Source: 10-K filed 2026-03-02, R3.htm
A3: https://www.sec.gov/Archives/edgar/data/1769628/000176962826000104/R3.htm
A4: Copied as shown. Column B = footnote marker column on the SEC page; [1] = footnote at the bottom of the table.
A6: CONSOLIDATED BALANCE SHEETS - USD ($) shares in Millions, $ in Millions | C6: Dec. 31, 2025 | D6: Dec. 31, 2024
A7: Current assets
A8: Cash and cash equivalents | C8: 3127 | D8: 1361
A9: Restricted cash and cash equivalents, current | C9: 819 | D9: 37
A10: Marketable securities | C10: 34 | D10: 0
A11: Accounts receivable, net | C11: 3169 | D11: 417
A12: Prepaid expenses and other current assets | C12: 339 | D12: 101
A13: Total current assets | C13: 7488 | D13: 1916
A14: Restricted cash and cash equivalents, non-current | C14: 184 | D14: 637
A15: Restricted marketable securities, non-current | C15: 0 | D15: 29
A16: Property and equipment, net | C16: 30557 | D16: 11915
A17: Operating lease right-of-use assets | C17: 8231 | D17: 2590
A18: Intangible assets, net | C18: 235 | D18: 5
A19: Goodwill | C19: 1101 | D19: 20
A20: Other non-current assets | B20: [1] | C20: 1506 | D20: 721
A21: Total assets | C21: 49302 | D21: 17833
A22: Current liabilities
A23: Accounts payable | C23: 1623 | D23: 868
A24: Accrued liabilities | C24: 5773 | D24: 356
A25: Debt, current | B25: [1] | C25: 6708 | D25: 2468
A26: Deferred revenue, current | C26: 1709 | D26: 769
A27: Operating lease liabilities, current | C27: 427 | D27: 213
A28: Finance lease liabilities, current | C28: 38 | D28: 58
A29: Other current liabilities | B29: [1] | C29: 162 | D29: 231
A30: Total current liabilities | C30: 16440 | D30: 4963
A31: Debt, non-current | B31: [1] | C31: 14665 | D31: 5458
A32: Derivative and warrant liabilities | C32: 1 | D32: 200
A33: Deferred revenue, non-current | C33: 6476 | D33: 3295
A34: Operating lease liabilities, non-current | C34: 7768 | D34: 2389
A35: Finance lease liabilities, non-current | C35: 216 | D35: 34
A36: Deferred tax liabilities, non-current | C36: 115 | D36: 149
A37: Other non-current liabilities | C37: 286 | D37: 37
A38: Total liabilities | C38: 45967 | D38: 16525
A39: Commitments and contingencies (Note 9)
A40: Stockholders' equity (deficit)
A41: Preferred stock, $0.000005 par value per share, 100 and no shares authorized as of December 31, 2025 and 2024, respectively; no shares issued and outstanding as of December 31, 2025 and 2024 | C41: 0 | D41: 0
A42: Treasury stock, at cost, 7 shares as of December 31, 2025 and 2024 | C42: -34 | D42: -34
A43: Additional paid-in capital | C43: 6012 | D43: 1096
A44: Accumulated deficit | C44: -2643 | D44: -1476
A45: Total stockholders' equity (deficit) | C45: 3335 | D45: -414
A46: Total liabilities, redeemable convertible preferred stock, and stockholders' equity (deficit) | C46: 49302 | D46: 17833
A47: Treasury stock (in shares) | C47: 7 | D47: 7
A48: Redeemable convertible preferred stock
A49: Redeemable convertible preferred stock
A50: Redeemable convertible preferred stock, $0.000005 par value per share, no and 206 shares authorized as of December 31, 2025 and 2024, respectively; no and 185 shares issued and outstanding as of December 31, 2025 and 2024, respectively | B50: [1] | C50: 0 | D50: 1722
A51: Common Class A
A52: Stockholders' equity (deficit)
A53: Common stock | C53: 0 | D53: 0
A54: Common Class B
A55: Stockholders' equity (deficit)
A56: Common stock | C56: 0 | D56: 0
A57: Common Class C
A58: Stockholders' equity (deficit)
A59: Common stock | C59: 0 | D59: 0
A61: [1] Refer to Note 14—Related-Party Transactions for further information on related party arrangements.
A63: Checks (added by us, NOT part of the SEC table) - all should be 0
A64: Current assets | C64: =SUM(C8:C12)-C13 | D64: =SUM(D8:D12)-D13
A65: Total assets | C65: =C13+SUM(C14:C20)-C21 | D65: =D13+SUM(D14:D20)-D21
A66: Current liabilities | C66: =SUM(C23:C29)-C30 | D66: =SUM(D23:D29)-D30
A67: Total liabilities | C67: =C30+SUM(C31:C37)-C38 | D67: =D30+SUM(D31:D37)-D38
A68: Stockholders' equity | C68: =SUM(C42:C44)-C45 | D68: =SUM(D42:D44)-D45
A69: Total L + redeemable pref + equity | C69: =C38+C50+C45-C46 | D69: =D38+D50+D45-D46
A70: Assets = L + pref + equity | C70: =C21-C46 | D70: =D21-D46

Sheet 10K_IS
A1: 10-K FY2025 - Consolidated Statements of Operations
A2: Source: 10-K filed 2026-03-02, R5.htm
A3: https://www.sec.gov/Archives/edgar/data/1769628/000176962826000104/R5.htm
A4: Copied as shown. Column B = footnote marker column.
A6: CONSOLIDATED STATEMENTS OF OPERATIONS AND COMPREHENSIVE LOSS - USD ($) shares in Millions, $ in Millions | C6: 12 Months Ended
C7: Dec. 31, 2025 | D7: Dec. 31, 2024 | E7: Dec. 31, 2023
A8: Income Statement [Abstract]
A9: Revenue | C9: 5131 | D9: 1915 | E9: 229
A10: Operating expenses:
A11: Cost of revenue | C11: 1453 | D11: 493 | E11: 69
A12: Technology and infrastructure | C12: 2929 | D12: 961 | E12: 131
A13: Sales and marketing | C13: 144 | D13: 18 | E13: 13
A14: General and administrative | C14: 651 | D14: 119 | E14: 30
A15: Total operating expenses | C15: 5177 | D15: 1591 | E15: 243
A16: Operating income (loss) | C16: -46 | D16: 324 | E16: -14
A17: Gain (loss) on fair value adjustments | C17: 27 | D17: -756 | E17: -534
A18: Interest expense, net | B18: [1] | C18: -1229 | D18: -361 | E18: -28
A19: Other income, net | C19: 33 | D19: 49 | E19: 18
A20: Loss before income taxes | C20: -1215 | D20: -744 | E20: -558
A21: Provision for (benefit from) income taxes | C21: -48 | D21: 119 | E21: 36
A22: Net loss and comprehensive loss | C22: -1167 | D22: -863 | E22: -594
A23: Net loss attributable to common stockholders, basic | C23: -1196 | D23: -937 | E23: -594
A24: Net loss attributable to common stockholders, diluted | C24: -1223 | D24: -937 | E24: -594
A25: Net loss per share attributable to common stockholders, basic (in usd per share ) | C25: -2.75 | D25: -4.3 | E25: -3.09
A26: Net loss per share attributable to common stockholders, diluted (in usd per share ) | C26: -2.81 | D26: -4.3 | E26: -3.09
A27: Weighted-average shares used in computing net loss per share attributable to common stockholders, basic (in shares) | C27: 435 | D27: 218 | E27: 192
A28: Weighted-average shares used in computing net loss per share attributable to common stockholders, diluted (in shares) | C28: 436 | D28: 218 | E28: 192
A30: [1] Refer to Note 14—Related-Party Transactions for further information on related party arrangements.
A32: Checks (added by us, NOT part of the SEC table) - all should be 0
A33: Total operating expenses | C33: =SUM(C11:C14)-C15 | D33: =SUM(D11:D14)-D15 | E33: =SUM(E11:E14)-E15
A34: Operating income | C34: =C9-C15-C16 | D34: =D9-D15-D16 | E34: =E9-E15-E16
A35: Loss before income taxes | C35: =SUM(C16:C19)-C20 | D35: =SUM(D16:D19)-D20 | E35: =SUM(E16:E19)-E20
A36: Net loss | C36: =C20-C21-C22 | D36: =D20-D21-D22 | E36: =E20-E21-E22

Sheet 10K_CF
A1: 10-K FY2025 - Consolidated Statements of Cash Flows
A2: Source: 10-K filed 2026-03-02, R8.htm
A3: https://www.sec.gov/Archives/edgar/data/1769628/000176962826000104/R8.htm
A4: Copied as shown ($ in millions).
A6: CONSOLIDATED STATEMENTS OF CASH FLOWS - USD ($) $ in Millions | B6: 12 Months Ended
B7: Dec. 31, 2025 | C7: Dec. 31, 2024 | D7: Dec. 31, 2023
A8: Cash flows from operating activities:
A9: Net loss | B9: -1167 | C9: -863 | D9: -594
A10: Adjustments to reconcile net loss to net cash provided by operating activities
A11: Depreciation and amortization | B11: 2454 | C11: 863 | D11: 103
A12: Amortization of debt discounts and issuance costs and accretion of redemption premiums | B12: 110 | C12: 33 | D12: 16
A13: Stock-based compensation expense | B13: 630 | C13: 31 | D13: 15
A14: Non-cash lease expense | B14: 357 | C14: 123 | D14: 20
A15: Deferred income taxes | B15: -53 | C15: 113 | D15: 36
A16: Loss (gain) on fair value adjustments | B16: -27 | C16: 756 | D16: 534
A17: Debt extinguishment loss | B17: 19 | C17: 12 | D17: 0
A18: Other non-cash reconciling items | B18: 103 | C18: 3 | D18: 1
A19: Changes in operating assets and liabilities, net of effect of business acquisitions:
A20: Accounts receivable | B20: -2749 | C20: -280 | D20: -162
A21: Prepaid expenses and other assets | B21: -784 | C21: -514 | D21: -139
A22: Accounts payable and accrued expenses | B22: 253 | C22: 511 | D22: 27
A23: Deferred revenue | B23: 4174 | C23: 2049 | D23: 1986
A24: Lease liabilities | B24: -262 | C24: -88 | D24: -9
A25: Other liabilities | B25: 0 | C25: 0 | D25: -1
A26: Net cash provided by operating activities | B26: 3058 | C26: 2749 | D26: 1833
A27: Cash flows from investing activities:
A28: Purchase of property and equipment, including capitalized internal-use software | B28: -10309 | C28: -8702 | D28: -2943
A29: Purchases of marketable securities | B29: -47 | C29: -34 | D29: -172
A30: Maturities and sales of marketable securities | B30: 43 | C30: 188 | D30: 6
A31: Sales of warrants received as lease incentive | B31: 254 | C31: 0 | D31: 0
A32: Business combinations, net of cash acquired | B32: -108 | C32: 0 | D32: 0
A33: Issuance of notes receivable | B33: -90 | C33: -60 | D33: 0
A34: Other investing activities | B34: -14 | C34: -50 | D34: -39
A35: Net cash used in investing activities | B35: -10271 | C35: -8658 | D35: -3148
A36: Cash flows from financing activities:
A37: Proceeds from issuance of debt, net | B37: 11829 | C37: 7018 | D37: 1404
A38: Repayments of debt | B38: -3399 | C38: -589 | D38: -2
A39: Purchase of capped calls related to convertible senior notes | B39: -340 | C39: 0 | D39: 0
A40: Proceeds from initial public offering, net of underwriting discounts and commissions | B40: 1491 | C40: 0 | D40: 0
A41: Redeemable convertible preferred stock cash dividends paid | B41: -29 | C41: -58 | D41: 0
A42: Issuance of redeemable convertible preferred stock, net of issuance costs | B42: 0 | C42: 1172 | D42: 421
A43: Payment of tax withholdings on settlement of restricted stock units | B43: -144 | C43: 0 | D43: 0
A44: Proceeds from exercise of stock options | B44: 20 | C44: 3 | D44: 2
A45: Proceeds from issuance of common stock | B45: 0 | C45: 0 | D45: 15
A46: Other financing activities | B46: -120 | C46: -82 | D46: -52
A47: Net cash provided by financing activities | B47: 9308 | C47: 7464 | D47: 1788
A48: Net increase in cash, cash equivalents, and restricted cash | B48: 2095 | C48: 1555 | D48: 473
... A50: Cash, cash equivalents, and restricted cash—end of period | B50: 4130 | C50: 2035 | D50: 480
A51: Supplemental disclosures of cash flow information:
A52: Cash paid for interest, net of capitalized amounts | B52: 869 | C52: 184 | D52: 0
A53: Non-cash investing and financing activities:
A54: Liabilities related to property and equipment additions, including OEM financed additions | B54: 11151 | C54: 893 | D54: 482
A55: Operating lease right-of-use assets acquired through lease liability | B55: 5836 | C55: 2222 | D55: 481
A56: Finance lease right-of-use assets acquired through lease liability | B56: 343 | C56: 142 | D56: 0
A57: Warrants received as lease incentive | B57: 222 | C57: 0 | D57: 0
A58: Conversion of redeemable convertible preferred stock in connection with initial public offering | B58: 1722 | C58: 0 | D58: 0
A59: Reclassification of redeemable Class A common stock to Class A common stock | B59: 1163 | C59: 0 | D59: 0
A60: Issuance of common stock, restricted stock units, and restricted stock awards for business combinations | B60: 1013 | C60: 0 | D60: 0
A61: Fair value of convertible promissory note issued for a business combination | B61: 167 | C61: 0 | D61: 0
A62: Issuance of common stock for contract incentive | B62: 350 | C62: 0 | D62: 0
A63: Reclassification of warrant liabilities to equity | B63: 173 | C63: 0 | D63: 0
A64: Issuance of common stock in connection with conversion of convertible notes | B64: 0 | C64: 1080 | D64: 0
A65: Reclassification of customer deposit to debt | B65: 230 | C65: 0 | D65: 0
... A69: Non-cash investments | B69: 77 | C69: 10 | D69: 0
A70: Reconciliation of cash, cash equivalents, and restricted cash to consolidated balance sheets:
A71: Cash and cash equivalents | B71: 3127 | C71: 1361 | D71: 217
A72: Restricted cash and cash equivalents, current | B72: 819 | C72: 37 | D72: 43
A73: Restricted cash and cash equivalents, non-current | B73: 184 | C73: 637 | D73: 220
A74: Total cash, cash equivalents, and restricted cash | B74: 4130 | C74: 2035 | D74: 480
A76: Checks (added by us, NOT part of the SEC table) - all should be 0
A77: Operating activities | B77: =SUM(B9:B25)-B26 | C77: =SUM(C9:C25)-C26 | D77: =SUM(D9:D25)-D26
A78: Investing activities | B78: =SUM(B28:B34)-B35 | C78: =SUM(C28:C34)-C35 | D78: =SUM(D28:D34)-D35
A79: Financing activities | B79: =SUM(B37:B46)-B47 | C79: =SUM(C37:C46)-C47 | D79: =SUM(D37:D46)-D47
A80: Net change in cash | B80: =B26+B35+B47-B48 | C80: =C26+C35+C47-C48 | D80: =D26+D35+D47-D48
A81: Cash roll-forward | B81: =B49+B48-B50 | C81: =C49+C48-C50 | D81: =D49+D48-D50
A82: Cash reconciliation | B82: =SUM(B71:B73)-B74 | C82: =SUM(C71:C73)-C74 | D82: =SUM(D71:D73)-D74

Sheet 10K_DebtText
A1: 10-K FY2025 - Note 10 Debt (full text)
A2: Source: 10-K filed 2026-03-02, R18.htm 'Debt'
A3: https://www.sec.gov/Archives/edgar/data/1769628/000176962826000104/R18.htm
A4: Full note text, word for word, one paragraph per row, in the original order. Column B repeats the nearest heading above (navigation only). Where SEC splits a paragraph across a page break it stays split. [TABLE] = a table in the note: Dec-25 tables not copied (superseded by the Q2 10-Q). Use this tab for terms of debt that the Q2 10-Q does not repeat (DDTL 1.0-3.0, 2030/2031 notes, 2031 converts, revolver history, OEM, Magnetar).
A6: ¶ | B6: Section (heading in source) | C6: Text (verbatim)
A7: 1 | B7: (note intro) | C7: The total debt obligations are as follows (dollars in millions):
A8: 2 | B8: (note intro) | C8: [TABLE]
A9: 3 | B9: (note intro) | C9: As of December 31, 2025, the future principal payments for the Company's total debt were as follows (in millions):
A10: 4 | B10: (note intro) | C10: [TABLE]
A11: 5 | B11: (note intro) | C11: The total interest expense for the Company's debt obligations was as follows (in millions):
A12: 6 | B12: (note intro) | C12: [TABLE]
A13: 7 | B13: (note intro) | C13: In the year ended December 31, 2025, the Company entered into DDTL Facilities and issued Senior Notes (each as defined in Note 10—Debt) as follows (dollars in millions):
A14: 8 | B14: (note intro) | C14: [TABLE]
A15: 9 | B15: (note intro) | C15: (1) DDTL Facilities are subject to an interest rate per annum equal to, at the Company's option, either the SOFR or the alternative base rate plus a spread.
A16: 10 | B16: (note intro) | C16: (2) Amounts represent borrowing capacity for the DDTL Facilities and the principal amounts for the Senior Notes.
A17: 11 | B17: Delayed Draw Term Loans ("DDTL") | C17: Delayed Draw Term Loans ("DDTL")
A18: 12 | B18: Delayed Draw Term Loans ("DDTL") | C18: In July 2023, the Company entered into a Delayed Draw Term Loan 1.0 Facility (as amended, the "DDTL 1.0 Facility"), which provided for a delayed draw term loan facility of up to $2.3 billion. The principal amount of the DDTL 1.0 Facility is required to be repaid in quarterly installments, with the final payment due on March 28, 2028.
... A71: 65 | B71: DCSP Financing Arrangements | C71: The DCSP Financing Arrangements allow for the net settlement of amounts due between the parties and meet the criteria for right of setoff in accordance with ASC 210, Balance Sheet. As of December 31, 2025, the gross amount of the DCSP Note Receivable was $304 million, which is presented net of the financing obligation and finance lease of $234 million. As of December 31, 2024, the gross amount of the DCSP Note Receivable was $224 million, which is presented net of the financing obligation of $116 million. The Company did not recognize any interest income during the year ended December 31, 2024, as the Company did not expect to be entitled to the accrued interest. The Company began recognizing interest income associated with this arrangement in March 2025. For the year ended December 31, 2025, the Company recognized $28 million of interest income in other income, net in the consolidated statements of operations and comprehensive loss. The total interest expense related to the financing obligation and finance lease associated with this arrangement for the year ended December 31, 2025 was $28 million and was not material for the years ended December 31, 2024 and 2023.

Sheet PR_Q2-26
A1: Q2 2026 Earnings Release - Non-GAAP Reconciliations
A2: Source: 8-K filed 2026-08-11 (Item 2.02), Exhibit 99.1
A3: https://www.sec.gov/Archives/edgar/data/1769628/000176962826000362/coreweave2q26earningspress.htm
A4: Company's own words (excerpt): To supplement our consolidated financial statements, which are prepared and presented in accordance with generally accepted accounting principles in the United States (“GAAP”), we use adjusted EBITDA and adjusted EBITDA margin, adjusted operating income (loss) and adjusted operating income (loss) margin, adjusted net income (loss) and adjusted net income (loss) margin, collectively, to help us evaluate our business. ... These non-GAAP financial measures are presented for supplemental informational purposes only, should not be considered a substitute for financial information presented in accordance with GAAP, and may be different from similarly titled non-GAAP measures used by other companies.
A6: Reconciliation of Net Loss to Adjusted EBITDA (in millions, except percentages)
B7: Three Months Ended June 30, | D7: Six Months Ended June 30,
B8: 2026 | C8: 2025 | D8: 2026 | E8: 2025
A9: Net loss | B9: -626 | C9: -290 | D9: -1366 | E9: -605
A10: Depreciation and amortization | B10: 1393 | C10: 559 | D10: 2540 | E10: 1003
A11: Interest expense, net | B11: 640 | C11: 267 | D11: 1176 | E11: 531
A12: Stock-based compensation | B12: 165 | C12: 145 | D12: 318 | E12: 329
A13: Provision for income taxes | B13: 62 | C13: 48 | D13: 146 | E13: 94
A14: Acquisition related costs(1) | B14: 1 | C14: 30 | D14: 2 | E14: 36
A15: Other (income) expense, net | B15: -125 | C15: -6 | D15: -149 | E15: -1
A16: (Gain) loss on fair value adjustments(2) | B16: 0 | C16: 0 | D16: 0 | E16: -27
A17: Adjusted EBITDA | B17: 1510 | C17: 753 | D17: 2667 | E17: 1360
A18: Revenue | B18: 2575 | C18: 1212 | D18: 4653 | E18: 2194
A19: Net loss margin | B19: -24 | C19: -24 | D19: -29 | E19: -28
A20: Adjusted EBITDA margin | B20: 59 | C20: 62 | D20: 57 | E20: 62
A21: (1) Acquisition related costs include direct transaction costs, such as due diligence, advisory, and professional services fees, and certain compensation and integration related expenses. We exclude acquisition related costs, as we believe these transaction-specific expenses are inconsistent in amount and frequency, and do not correlate to the operation of our business.
A22: (2) Represents adjustments related to recording our derivative liabilities at fair value at the end of each reporting period for our 2021 Convertible Senior Secured Notes, warrant liabilities related to our 2022 Senior Secured Notes, and the fair value remeasurement of the option liability in connection with our Series B redeemable convertible preferred stock. Refer to Note 3. Investments and Fair Value Measurements to our consolidated financial statements included in our Quarterly Report on Form 10-Q filed or to be filed with the SEC for the quarter ended June 30, 2026 for additional information.
A24: Reconciliation of Operating Loss to Adjusted Operating Income (in millions, except percentages)
B25: Three Months Ended June 30, | D25: Six Months Ended June 30,
B26: 2026 | C26: 2025 | D26: 2026 | E26: 2025
A27: Operating income (loss) | B27: -49 | C27: 19 | D27: -193 | E27: -8
A28: Stock-based compensation | B28: 165 | C28: 145 | D28: 318 | E28: 329
A29: Acquisition related costs(1) | B29: 1 | C29: 30 | D29: 2 | E29: 36
A30: Amortization of acquired intangibles(2) | B30: 11 | C30: 6 | D30: 22 | E30: 6
A31: Adjusted operating income | B31: 128 | C31: 200 | D31: 149 | E31: 363
A32: Revenue | B32: 2575 | C32: 1212 | D32: 4653 | E32: 2194
A33: Operating income (loss) margin | B33: -2 | C33: 2 | D33: -4 | E33: 0
A34: Adjusted operating income margin | B34: 5 | C34: 16 | D34: 3 | E34: 17
A35: (1) Acquisition related costs include direct transaction costs, such as due diligence, advisory, and professional services fees, and certain compensation and integration related expenses. We exclude acquisition related costs, as we believe these transaction-specific expenses are inconsistent in amount and frequency, and do not correlate to the operation of our business.
A36: (2) In the second quarter of 2025, we began including an adjustment for the amortization of acquired intangibles in our calculation of adjusted operating income. Prior period non-GAAP calculations for acquired intangible amortization are not being adjusted as these amounts were insignificant.
A38: Reconciliation of Net Loss to Adjusted Net Loss (in millions, except percentages)
B39: Three Months Ended June 30, | D39: Six Months Ended June 30,
B40: 2026 | C40: 2025 | D40: 2026 | E40: 2025
A41: Net loss | B41: -626 | C41: -290 | D41: -1366 | E41: -605
A42: Stock-based compensation | B42: 165 | C42: 145 | D42: 318 | E42: 329
A43: Loss on extinguishment of debt(1) | B43: 0 | C43: 9 | D43: 0 | E43: 10
A44: Acquisition related costs(2) | B44: 1 | C44: 30 | D44: 2 | E44: 36
A45: Amortization of acquired intangibles(3) | B45: 11 | C45: 6 | D45: 22 | E45: 6
A46: (Gain) loss on fair value adjustments(4) | B46: 0 | C46: 0 | D46: 0 | E46: -27
A47: Other adjustments(5) | B47: -109 | C47: -11 | D47: -109 | E47: -11
A48: Income tax, inclusive of the tax effect of the above adjustments(6) | B48: -9 | C48: -19 | D48: -23 | E48: -19
A49: Adjusted net loss | B49: -567 | C49: -130 | D49: -1156 | E49: -281
A50: Revenue | B50: 2575 | C50: 1212 | D50: 4653 | E50: 2194
A51: Net loss margin | B51: -24 | C51: -24 | D51: -29 | E51: -28
A52: Adjusted net loss margin | B52: -22 | C52: -11 | D52: -25 | E52: -13
A53: (1) Primarily relates to losses recognized upon the early extinguishment of certain OEM financing arrangements, as well as accelerated amortization of debt discount and debt issuance costs related to our 2024 Term Loan, which was repaid in connection with the IPO.
A54: (2) Acquisition related costs - same text as above.
A55: (3) In the second quarter of 2025, we began including an adjustment for the amortization of acquired intangibles in our calculation of adjusted net loss. Prior period non-GAAP calculations for acquired intangible amortization are not being adjusted as these amounts were insignificant.
A56: (4) Fair value adjustments - same text as footnote (2) of the Adjusted EBITDA table.
A57: (5) Primarily relates to a net unrealized gain on our investments.
A58: (6) In the second quarter of 2025, we began including an adjustment for the income tax effect related to our non-GAAP adjustments. Prior period non-GAAP calculations for the income tax effects on our non-GAAP adjustments are not being adjusted as these amounts were not material. [... continues in source]
A60: Checks (added by us, NOT part of the press release) - all should be 0
A61: Adjusted EBITDA = sum of reconciling items | B61: =SUM(B9:B16)-B17 | C61: =SUM(C9:C16)-C17 | D61: =SUM(D9:D16)-D17 | E61: =SUM(E9:E16)-E17
A62: Adjusted operating income = sum of items | B62: =SUM(B27:B30)-B31 | C62: =SUM(C27:C30)-C31 | D62: =SUM(D27:D30)-D31 | E62: =SUM(E27:E30)-E31
A63: Adjusted net loss = sum of items | B63: =SUM(B41:B48)-B49 | C63: =SUM(C41:C48)-C49 | D63: =SUM(D41:D48)-D49 | E63: =SUM(E41:E48)-E49

Sheet PR_Q4-25
A1: Q4 2025 Earnings Release - Non-GAAP Reconciliations
A2: Source: 8-K filed 2026-02-26 (Item 2.02), Exhibit 99.1
A3: https://www.sec.gov/Archives/edgar/data/1769628/000176962826000094/coreweave4q25earningspress.htm
A4: Company's own words (excerpt): To supplement our consolidated financial statements, which are prepared and presented in accordance with generally accepted accounting principles in the United States (“GAAP”), we use adjusted EBITDA and adjusted EBITDA margin, adjusted operating income (loss) and adjusted operating income (loss) margin, adjusted net income (loss) and adjusted net income (loss) margin, collectively, to help us evaluate our business. ... These non-GAAP financial measures are presented for supplemental informational purposes only, should not be considered a substitute for financial information presented in accordance with GAAP, and may be different from similarly titled non-GAAP measures used by other companies.
A6: Reconciliation of Net Loss to Adjusted EBITDA (in millions, except percentages)
B7: Three Months Ended December 31, | D7: Twelve Months Ended December 31,
B8: 2025 | C8: 2024 | D8: 2025 | E8: 2024
A9: Net loss | B9: -452 | C9: -51 | D9: -1167 | E9: -863
A10: Depreciation and amortization | B10: 821 | C10: 365 | D10: 2454 | E10: 863
A11: Interest expense, net | B11: 388 | C11: 149 | D11: 1229 | E11: 361
A12: Stock-based compensation | B12: 157 | C12: 8 | D12: 630 | E12: 31
A13: Acquisition related costs(1) | B13: 9 | C13: 0 | D13: 55 | E13: 0
A14: (Gain) loss on fair value adjustments(2) | B14: 0 | C14: 7 | D14: -27 | E14: 756
A15: Other income, net | B15: -10 | C15: -14 | D15: -33 | E15: -48
A16: Provision for (benefit from) income taxes | B16: -15 | C16: 22 | D16: -48 | E16: 119
A17: Adjusted EBITDA | B17: 898 | C17: 486 | D17: 3093 | E17: 1219
A18: Revenue | B18: 1572 | C18: 747 | D18: 5131 | E18: 1915
A19: Net loss margin | B19: -29 | C19: -7 | D19: -23 | E19: -45
A20: Adjusted EBITDA margin | B20: 57 | C20: 65 | D20: 60 | E20: 64
A21: (1) Acquisition related costs include direct transaction costs, such as due diligence, advisory, and professional services fees, and certain compensation and integration related expenses. We exclude acquisition related costs, as we believe these transaction-specific expenses are inconsistent in amount and frequency, and do not correlate to the operation of our business.
A22: (2) Represents adjustments related to recording our derivative liabilities at fair value at the end of each reporting period for our 2021 Convertible Senior Secured Notes, warrant liabilities related to our 2022 Senior Secured Notes, and the fair value remeasurement of the option liability in connection with our Series B redeemable convertible preferred stock. Refer to Note 3. Investments and Fair Value Measurements to our consolidated financial statements included in our Annual Report on Form 10-K filed or to be filed with the SEC for the year ended December 31, 2025 for additional information.
A24: Reconciliation of Operating Income to Adjusted Operating Income (in millions, except percentages)
B25: Three Months Ended December 31, | D25: Twelve Months Ended December 31,
B26: 2025 | C26: 2024 | D26: 2025 | E26: 2024
A27: Operating income (loss) | B27: -89 | C27: 113 | D27: -46 | E27: 324
A28: Stock-based compensation | B28: 157 | C28: 8 | D28: 630 | E28: 32
A29: Acquisition related costs(1) | B29: 9 | C29: 0 | D29: 55 | E29: 0
A30: Amortization of acquired intangibles(2) | B30: 11 | C30: 0 | D30: 27 | E30: 0
A31: Adjusted operating income | B31: 88 | C31: 121 | D31: 666 | E31: 356
A32: Revenue | B32: 1572 | C32: 747 | D32: 5131 | E32: 1915
A33: Operating income margin | B33: -6 | C33: 15 | D33: -1 | E33: 17
A34: Adjusted operating income margin | B34: 6 | C34: 16 | D34: 13 | E34: 19
A35: (1) Acquisition related costs include direct transaction costs, such as due diligence, advisory, and professional services fees, and certain compensation and integration related expenses. We exclude acquisition related costs, as we believe these transaction-specific expenses are inconsistent in amount and frequency, and do not correlate to the operation of our business.
A36: (2) In the second quarter of 2025, we began including an adjustment for the amortization of acquired intangibles in our calculation of adjusted operating income (loss). Prior period non-GAAP calculations for acquired intangible amortization are not being adjusted as these amounts were insignificant.
A38: Reconciliation of Net Loss to Adjusted Net Loss (in millions, except percentages)
B39: Three Months Ended December 31, | D39: Twelve Months Ended December 31,
B40: 2025 | C40: 2024 | D40: 2025 | E40: 2024
A41: Net loss | B41: -452 | C41: -51 | D41: -1167 | E41: -863
A42: Stock-based compensation | B42: 157 | C42: 8 | D42: 630 | E42: 31
A43: Loss on extinguishment of debt(1) | B43: 4 | C43: 0 | D43: 29 | E43: 0
A44: Acquisition related costs(2) | B44: 9 | C44: 0 | D44: 55 | E44: 0
A45: Amortization of acquired intangibles(3) | B45: 11 | C45: 0 | D45: 27 | E45: 0
A46: (Gain) loss on fair value adjustments(4) | B46: 0 | C46: 7 | D46: -27 | E46: 756
A47: Other adjustments(5) | B47: 0 | C47: 0 | D47: -23 | E47: 11
A48: Income tax, inclusive of the tax effect of the above adjustments(6) | B48: -13 | C48: 0 | D48: -130 | E48: 0
A49: Adjusted net loss | B49: -284 | C49: -36 | D49: -606 | E49: -65
A50: Revenue | B50: 1572 | C50: 747 | D50: 5131 | E50: 1915
A51: Net loss margin | B51: -29 | C51: -7 | D51: -23 | E51: -45
A52: Adjusted net loss margin | B52: -18 | C52: -5 | D52: -12 | E52: -3
A53: (1) Primarily relates to losses recognized upon the early extinguishment of certain OEM financing arrangements, as well as accelerated amortization of debt discount and debt issuance costs related to our 2024 Term Loan, which was repaid in connection with the IPO.
A54: (2) Acquisition related costs - same text as above.
A55: (3) In the second quarter of 2025, we began including an adjustment for the amortization of acquired intangibles in our calculation of adjusted net loss. Prior period non-GAAP calculations for acquired intangible amortization are not being adjusted as these amounts were insignificant.
A56: (4) Fair value adjustments - same text as footnote (2) of the Adjusted EBITDA table.
A57: (5) Primarily relates to a net unrealized gain on our strategic investments.
A58: (6) In the second quarter of 2025, we began including an adjustment for the income tax effect related to our non-GAAP adjustments. Prior period non-GAAP calculations for the income tax effects on our non-GAAP adjustments are not being adjusted as these amounts were not material. [... continues in source]
A60: Checks (added by us, NOT part of the press release) - all should be 0
A61: Adjusted EBITDA = sum of reconciling items | B61: =SUM(B9:B16)-B17 | C61: =SUM(C9:C16)-C17 | D61: =SUM(D9:D16)-D17 | E61: =SUM(E9:E16)-E17
A62: Adjusted operating income = sum of items | B62: =SUM(B27:B30)-B31 | C62: =SUM(C27:C30)-C31 | D62: =SUM(D27:D30)-D31 | E62: =SUM(E27:E30)-E31
A63: Adjusted net loss = sum of items | B63: =SUM(B41:B48)-B49 | C63: =SUM(C41:C48)-C49 | D63: =SUM(D41:D48)-D49 | E63: =SUM(E41:E48)-E49

Sheet Subsequent
A1: Subsequent events known on the analysis date (2026-08-13)
A2: Word for word. Events AFTER 2026-08-13 are deliberately excluded (e.g., the September 2026 convertible notes).
A4: ¶ | B4: Document / section | C4: Text (verbatim)
A5: A. 10-Q Q2 2026, Note 16 - Subsequent Events
A6: https://www.sec.gov/Archives/edgar/data/1769628/000176962826000366/R22.htm
A7: 1 | B7: Note 16 | C7: In August 2026, one of the Company's indirect subsidiaries, CoreWeave Financing DDTL V-V, LLC entered into a delayed draw term loan facility agreement with various lenders and JPMorgan Chase Bank, N.A., as the administrative agent. The agreement provides a $2.6 billion delayed draw term loan facility (the “DDTL 5.5 Facility”) available in one or more draws through the commitment termination date in December 2026. Interest on outstanding borrowings on the DDTL 5.5 Facility accrues for SOFR loans at an interest rate per annum equal to the Term SOFR plus an applicable margin of 5.5% or for base rate loans at the applicable base rate plus 4.5% per annum, at the Company's election. The DDTL 5.5 Facility matures in September 2031. Subsequent to the closing, the Company has drawn $1.2 billion.
A8: 2 | B8: Note 16 | C8: In August 2026, the Company made a $1.2 billion draw down on the Revolving Credit Facility.
A10: B. 8-K filed 2026-08-10 (event date 2026-08-07), Items 1.01 and 2.03
A11: https://www.sec.gov/Archives/edgar/data/1769628/000176962826000357/crwv-20260807.htm
A12: 1 | B12: 8-K body | C12: Item 1.01 Entry into a Material Definitive Agreement.On August 7, 2026, CoreWeave Financing DDTL V-V, LLC (the “Borrower”), a Delaware limited liability company and an indirect subsidiary of CoreWeave, Inc., a Delaware corporation (the “Parent”), entered into a credit agreement (the “Credit Agreement”) with, inter alios, JPMorgan Chase Bank, N.A., as administrative agent, U.S. Bank Trust Company, National Association, as collateral agent, U.S. Bank National Association, as depositary bank, JPMorgan Chase Bank, N.A. and MUFG Bank, Ltd. as joint lead arrangers, joint bookrunners and syndication agents, and the lenders party thereto, providing for a $2.6 billion delayed draw term loan facility (the “DDTL 5.5 Facility”). The DDTL 5.5 Facility was entered into primarily to finance capital expenditures required to perform certain customer contracts, including the acquisition of GPU servers and related infrastructure.
A13: 2 | B13: 8-K body | C13: Availability and MaturityThe DDTL 5.5 Facility provides for delayed draw term loans available in one or more draws until the commitment termination date in December 2026. The maturity date of the DDTL 5.5 Facility is September 1, 2031.
A14: 3 | B14: 8-K body | C14: Interest Rate and FeesAmounts borrowed under the DDTL 5.5 Facility are subject to an interest rate per annum equal to (i) for SOFR loans, Term SOFR (subject to a 0.00% floor) plus an applicable margin of 5.50% per annum, and (ii) for base rate loans, the base rate (determined by reference to the highest of (A) the prime rate, (B) the federal funds effective rate plus 0.50% and (C) Term SOFR for a one-month tenor plus 1.00%) (subject to a 0.00% floor), plus an applicable margin of 4.50% per annum. The DDTL 5.5 Facility provides for payment of, among others, undrawn fees in an amount equal to 0.50% per annum on the average daily undrawn portion of the DDTL 5.5 Facility, which undrawn fees are payable monthly in arrears.
A15: 4 | B15: 8-K body | C15: Guarantees and SecurityAll obligations under the DDTL 5.5 Facility are unconditionally guaranteed by the Parent pursuant to a parent guarantee and pledge agreement, dated as of August 7, 2026, by and among the Parent, CW Financing DDTL V-V Holdco, LLC, a Delaware limited liability company, and U.S. Bank Trust Company, National Association (the “Parent Guarantee and Pledge Agreement”), and all obligations under the DDTL 5.5 Facility are also unconditionally guaranteed by the subsidiaries of the Borrower pursuant to a collateral agreement. All obligations under the DDTL 5.5 Facility are secured by substantially all assets of the Borrower and its subsidiaries and a pledge of 100% of the equity interests in the Borrower held by CW Financing DDTL V-V Holdco, LLC.
A16: 5 | B16: 8-K body | C16: CovenantsThe Borrower is required to comply with the following covenants, among others described in the Credit Agreement:
A17: 6 | B17: 8-K body | C17: Debt Service Coverage Ratio. Beginning the first full calendar month after the earlier to occur of (a) the date on which the commitments are reduced to zero and (b) December 31, 2026, the Borrower is required to maintain a debt service coverage ratio of at least 1.35x.
A18: 7 | B18: 8-K body | C18: Certain Other Covenants and Events of Default. The DDTL 5.5 Facility contains a number of other customary negative covenants, and the Credit Agreement contains customary events of default, including payment defaults, failure to perform or observe covenants, cross-defaults with certain other indebtedness, a change of control, and certain bankruptcy events. The Credit Agreement also contains events of default related to certain adverse events with respect to certain material contracts.
A19: 8 | B19: 8-K body | C19: The foregoing summary of the DDTL 5.5 Facility does not purport to be complete and is qualified in its entirety by reference to the complete terms of the Credit Agreement and the Parent Guarantee and Pledge Agreement, which are filed as Exhibits 10.1 and 10.2 hereto respectively, and incorporated by reference into this Item 1.01.
A20: 9 | B20: 8-K body | C20: Item 2.03 Creation of a Direct Financial Obligation or an Obligation under an Off-Balance Sheet Arrangement of a Registrant.The information described above under Item 1.01 is incorporated into this Item 2.03 by reference.
A22: C. Same 8-K, Exhibit 99.1 press release (closing 'About CoreWeave' boilerplate omitted)
A23: https://www.sec.gov/Archives/edgar/data/1769628/000176962826000357/ex991pr.htm
A24: 1 | B24: Ex.99.1 | C24: COREWEAVE CLOSES $2.6 BILLION LOAN FACILITY, EXPANDING FINANCING FLEXIBILITY FOR AI INFRASTRUCTURE
A25: 2 | B25: Ex.99.1 | C25: ●Facility is backed by a diverse group of leading AI, financial services, and technology customers
A26: 3 | B26: Ex.99.1 | C26: ●Facility’s approximate five-year maturity extends beyond the average three-year length of underlying customer contracts, reflecting lender confidence in long-term GPU demand
A27: 4 | B27: Ex.99.1 | C27: ●Innovative structure allows CoreWeave to efficiently finance shorter-dated contracts, unlocking a broader base of enterprise customers and higher-margin deals
A28: 5 | B28: Ex.99.1 | C28: LIVINGSTON, N.J. — AUGUST 10, 2026 — CoreWeave, Inc. (Nasdaq: CRWV), The Essential Cloud for AI™, today announced it has closed its $2.6 billion delayed draw term loan facility (“DDTL 5.5 Facility”), supporting the continued expansion of its AI cloud platform and committed customer deployments.
A29: 6 | B29: Ex.99.1 | C29: The DDTL 5.5 Facility extends CoreWeave’s HPC infrastructure-backed financing platform by broadening the scope of customer contracts eligible for publicly syndicated infrastructure financing. Unlike prior delayed draw term loan facilities backed by customer contracts extending through the maturity of the debt, the DDTL 5.5 Facility carries an approximate five-year maturity while its underlying customer contracts average approximately three years in length. By financing these shorter-date commitments, lenders are signalling confidence in the long-term value of NVIDIA GPUs running on CoreWeave’s cloud platform and a willingness to underwrite renewal risk. These shorter duration customer contracts also often command higher prices, which CoreWeave expects to allow it to capture higher margins while expanding market reach.
A30: 7 | B30: Ex.99.1 | C30: “This transaction demonstrates the continued evolution and growing flexibility of AI infrastructure financing and represents a major unlock for CoreWeave,” said Brannin McBee, co-founder and chief development officer at CoreWeave. “Lenders are now comfortable financing shorter-dated contracts, which allows us to target a wider variety of customers, including global enterprises that typically favor shorter-term agreements.”
A31: 8 | B31: Ex.99.1 | C31: The facility received ratings of Ba2 from Moody’s and BB+ from Fitch, reflecting the strength of the collateral and structural protections supporting the transaction.
A32: 9 | B32: Ex.99.1 | C32: Proceeds from the DDTL 5.5 Facility will support the purchase and deployment of HPC-backed infrastructure dedicated to customer contracts. The facility includes the option for CoreWeave to either renew existing contracts or re-lease capacity to other customers at the end of the initial underlying contracts, subject to the criteria described in the credit agreement for the DDTL 5.5 Facility.
A33: 10 | B33: Ex.99.1 | C33: The transaction was meaningfully oversubscribed, attracting exceptional investor demand, and priced at SOFR + 5.50%. The DDTL 5.5 Facility was issued through CoreWeave Financing DDTL V-V, LLC.
A34: 11 | B34: Ex.99.1 | C34: JPMorgan and Mitsubishi UFJ Financial Group served as joint lead arrangers and bookrunners for the transaction.
A35: 12 | B35: Ex.99.1 | C35: The DDTL 5.5 Facility builds on CoreWeave’s continued capital markets momentum and follows the company’s previously announced $3.1 billion DDTL 5.0 facility completed earlier this year. With the closing of this transaction, CoreWeave has secured more than $30 billion of debt and equity capital year-to-date, representing a significant step in CoreWeave's evolution as it continues to scale its global footprint and service offerings for a larger and more diverse set of customers.
A37: D. Same 8-K, Exhibit 10.2 Parent Guarantee and Pledge Agreement - Section 2.1(a)-(b) only (the full agreement is ~98,000 characters)
A38: https://www.sec.gov/Archives/edgar/data/1769628/000176962826000357/ex102parentguarantee.htm
A39: 1 | B39: Ex.10.2 s.2.1 | C39: Section 2.1Guarantee.(a)Subject to the provisions of Section 2.1(b), the Guarantor hereby unconditionally and irrevocably guarantees, as a primary obligor and not merely a surety, the prompt and complete payment and performance when due (whether at the stated maturity, by acceleration, demand or otherwise) of the Guaranteed Obligations and whether at stated maturity, by acceleration, demand or otherwise, and whether such Guaranteed Obligations are now existing or hereafter incurred (including any extensions, modifications, substitutions, amendments and renewals of any or all of such Guaranteed Obligations). Guarantor further agrees that the Guaranteed Obligations may be extended, increased, renewed, amended or modified, in whole or in part, without notice to, or further assent from Guarantor, and that Guarantor will remain bound upon its guarantee hereunder notwithstanding any such extension, increase, renewal, amendment or modification of any Guaranteed Obligations. Guarantor waives, to the fullest extent permitted under applicable Law, presentment to, demand of payment from, and protest to, the Borrower or any other Person of any of the Guaranteed Obligations, and also waives, to the fullest extent permitted under applicable Law, notice of acceptance of its guarantee and notice of protest for nonpayment.
A40: 2 | B40: Ex.10.2 s.2.1 | C40: (b)Anything herein or in the Credit Agreement to the contrary notwithstanding, as of any date of determination the maximum liability of the Guarantor hereunder shall in no event exceed the amount that is the lesser of (i) the outstanding Guaranteed Obligations as of such date of determination and (ii) the maximum liability which can be guaranteed by the Guarantor under the Bankruptcy Code or any applicable federal and state requirements of Law relating to fraudulent conveyances, fraudulent transfers or the insolvency of debtors.

Sheet Guidance
A1: Company guidance and capex definition - Q2 2026 earnings materials (2026-08-11)
A2: Word for word from the company's IR website (investors.coreweave.com > Financials > Quarterly Results). Guidance is forward-looking and not in the 10-Q. Anything published after 2026-08-13 (e.g., Q3'26 results) is excluded.
A4: A. Q3 and FY 2026 Outlook Presentation, slide 3 'Guidance'
A5: https://s205.q4cdn.com/133937190/files/doc_financials/2026/q2/CoreWeave-Q2-26-Earnings-Outlook-Presentation.pdf
A6: Q3'26 Guidance | D6: FY'26 Guidance
A7: Revenue | B7: $3.45 – 3.60 billion | D7: Revenue | E7: $12.4 – 13.2 billion
A8: Adjusted Operating Income | B8: $200 – 260 million | D8: Adjusted Operating Income | E8: $960 – 1,150 million
A9: Interest Expense | B9: $860 – 940 million | D9: Capital Expenditures | E9: $35 – 39 billion
A10: Capital Expenditures | B10: $11.5 – 13.5 billion | D10: Exiting 2026 ARR 1 | E10: $18.5 – 19.5 billion
A11: Note: 1. Annualized run-rate revenue (ARR) is calculated by taking revenue from the last month of the quarter multiplied by 12
A13: B. Q2'26 Earnings Presentation - slide 16 'Capital Expenditures Calculation' (in millions)
A14: https://s205.q4cdn.com/133937190/files/doc_financials/2026/q2/CoreWeave-Q2-26-Earnings-Presentation.pdf
B15: Three Months Ended June 30, | D15: Six Months Ended June 30,
B16: 2025 | C16: 2026 | D16: 2025 | E16: 2026
A17: Increase in total gross property and equipment | B17: 2975 | C17: 11689 | D17: 5705 | E17: 18681
A18: Less: Change in construction in progress | B18: 37 | C18: 2337 | D18: 910 | E18: 2542
A19: Capital expenditures 1 | B19: 2938 | C19: 9352 | D19: 4795 | E19: 16139
A20: Check: increase - change in CIP - capex (should be 0) | B20: =B17-B18-B19 | C20: =C17-C18-C19 | D20: =D17-D18-D19 | E20: =E17-E18-E19
A21: Note: 1. Capital expenditures are additions to property and equipment including assets acquired under finance leases, less changes in construction in progress
A23: Slide 14 'Capital Expenditures' chart (Note: $ in billions)
B24: Q2'25 | C24: Q3'25 | D24: Q4'25 | E24: Q1'26 | F24: Q2'26
A25: Capital Expenditures 1 | B25: 2.9 | C25: 1.9 | D25: 8.2 | E25: 6.8 | F25: 9.4
A26: Slide title: 'Capital Expenditures: $9.4 billion as we continued to execute on schedule'
A27: Note: 1. Capital expenditures are additions to property and equipment including assets acquired under finance leases, less changes in construction in progress
A28: Slide 8 'Q2'26 Highlights', note 3 (worded slightly differently): 3. Capital expenditures are additions to property and equipment plus assets acquired under finance leases, less changes to construction in progress
A30: C. Q2 2026 earnings call, 2026-08-11 - key points (paraphrased; the transcript is FactSet copyright, see link)
A31: https://s205.q4cdn.com/133937190/files/doc_financials/2026/q2/CRWV-US-CORRECTED-TRANSCRIPT-CoreWeave-Q2-2026-Earnings-Call-11August2026.pdf
A32: ¶ | B32: Speaker | C32: Key points (paraphrased, figures as stated on the call)
A33: 1 | B33: Nitin Agrawal, CFO (prepared remarks) | C33: Q2 capex was $9.4bn, slightly above the high end of guidance; construction in progress rose to $11.9bn from $9.6bn, capacity expected to be deployed early in Q3.
A34: 2 | B34: Nitin Agrawal, CFO (prepared remarks) | C34: At June 30 the company had more than $6.9bn of cash, cash equivalents, restricted cash and marketable securities; it raised about $18bn across debt, convertibles and equity in Q2.
A35: 3 | B35: Nitin Agrawal, CFO (prepared remarks) | C35: Year-end active power now expected above 1.85 GW (previously above 1.7 GW); Q3 revenue guided to $3.45-3.6bn and Q3 adjusted operating income to $200-260m.
A36: 4 | B36: Nitin Agrawal, CFO (prepared remarks) | C36: Q3 interest expense guided to $860-940m, reflecting a larger debt balance; Q3 capex guided to $11.5-13.5bn.
A37: 5 | B37: Nitin Agrawal, CFO (prepared remarks) | C37: FY26 guidance raised: revenue $12.4-13.2bn, adjusted operating income $0.96-1.15bn, capex $35-39bn, exiting-2026 ARR $18.5-19.5bn.
A38: 6 | B38: Irvin Liu, Evercore ISI (Q&A question) | C38: Analyst question referenced a target of more than 3 GW of active power by end-2027 and 8 GW by 2030.
A39: 7 | B39: Nitin Agrawal, CFO (Q&A answer) | C39: CFO: 4.2 GW contracted today plus ~1.5 GW of powered land/options; on track for more than 8 GW of active power by end-2030.
A40: Paraphrased from the corrected transcript linked above; see the original for exact wording.

Sheet Cross_Checks
A1: Cross-document checks (ours) - the same number should match across filings
A2: Green = link to another tab. Difference column should be 0; where it is not, the Comment explains why.
A4: Check | B4: Value A | C4: Value B | D4: Difference | E4: Comment
A5: Total assets Dec-25: 10-Q comparative vs 10-K | B5: ='10Q_BS'!C20 | C5: ='10K_BS'!C21 | D5: =B5-C5
A6: Debt, current Dec-25: 10-Q (recourse + non-recourse) vs 10-K (one line) | B6: ='10Q_BS'!C24+'10Q_BS'!C25 | C6: ='10K_BS'!C25 | D6: =B6-C6 | E6: 10-K showed one 'Debt' line; the 10-Q re-presents Dec-25 split into recourse / non-recourse
A7: Debt, non-current Dec-25: 10-Q split vs 10-K | B7: ='10Q_BS'!C31+'10Q_BS'!C32 | C7: ='10K_BS'!C31 | D7: =B7-C7
A8: Other non-current liabilities Dec-25: 10-Q vs 10-K (other + derivative/warrant) | B8: ='10Q_BS'!C37 | C8: ='10K_BS'!C37+'10K_BS'!C32 | D8: =B8-C8 | E8: 10-Q folds the 10-K's 'Derivative and warrant liabilities' line into 'Other'
A9: Total equity Dec-25: 10-Q vs 10-K | B9: ='10Q_BS'!C46 | C9: ='10K_BS'!C45 | D9: =B9-C9
A10: Cash end of 6M26 (CF, thousands /1000) vs BS cash + restricted | B10: ='10Q_CF'!B47/1000 | C10: ='10Q_BS'!B8+'10Q_BS'!B9+'10Q_BS'!B14 | D10: =B10-C10 | E10: R page CF is in thousands
A11: Net loss 6M26: 10-Q CF (/1000) vs 10-Q IS | B11: ='10Q_CF'!B9/1000 | C11: ='10Q_IS'!D22 | D11: =B11-C11
A12: Net loss Q2-26: press release vs 10-Q IS | B12: ='PR_Q2-26'!B9 | C12: ='10Q_IS'!B22 | D12: =B12-C12
A13: Operating income 6M26: press release vs 10-Q IS | B13: ='PR_Q2-26'!D27 | C13: ='10Q_IS'!D16 | D13: =B13-C13
A14: Interest expense 6M26: press release (add-back) vs 10-Q IS | B14: ='PR_Q2-26'!D11 | C14: =-'10Q_IS'!D18 | D14: =B14-C14 | E14: Sign flips: IS shows expense as negative; reconciliation adds it back
A15: D&A 6M26: press release vs 10-Q CF (/1000) | B15: ='PR_Q2-26'!D10 | C15: ='10Q_CF'!B11/1000 | D15: =B15-C15
A16: Net loss FY25: Q4 release vs 10-K IS | B16: ='PR_Q4-25'!D9 | C16: ='10K_IS'!C22 | D16: =B16-C16
A17: Other income FY24: Q4 release EBITDA table vs 10-K IS | B17: =-'PR_Q4-25'!E15 | C17: ='10K_IS'!D19 | D17: =B17-C17 | E17: Release subtracts 48; IS shows 49 - a 1mm inconsistency in the company's own tables
A18: SBC FY24: EBITDA table vs Adj. operating income table | B18: ='PR_Q4-25'!E12 | C18: ='PR_Q4-25'!E28 | D18: =B18-C18 | E18: 31 vs 32 in the same release

Sheet Debt Database
A1: Instrument | B1: Type | C1: Status | D1: Borrower Entity | E1: Recourse | F1: Secured | G1: Parent Guarantee | H1: Commitment ($mm) | I1: Principal 6/30 ($mm) | J1: Subsequent Draws ($mm) | K1: Pro Forma Principal ($mm) | L1: Undrawn 8/13 ($mm) | M1: Fixed/Floating | N1: Coupon/Spread | O1: Effective Rate | P1: Maturity | Q1: Amortizing/Bullet | R1: Collateral/Backing | S1: Source | T1: Draw Period End | U1: Availability Reductions ($mm) | V1: Undrawn 6/30 ($mm) | W1: Annual Interest @ Effective Rate ($mm) | X1: Maturity Year
A2: DDTL 1.0 Facility | B2: DDTL | C2: Reported 6/30 | D2: Subsidiary (not named in filings used) | E2: Recourse | F2: Secured | G2: Full | H2: 2300 | I2: ='10Q_Debt'!D9 | J2: 0 | K2: =I2+J2 | L2: =IF(ISNUMBER(T2),IF(T2>=$B$24,H2-K2-U2,0),0) | M2: Floating | N2: SOFR or ABR + spread (spread not disclosed) | O2: ='10Q_Debt'!C9 | P2: 46840 | Q2: Amortizing | R2: Subsidiary equity + substantially all subsidiary assets (GPU servers); related customer contracts (10Q ¶30) | S2: Q2'26 10-Q, Note 10, p.27 (T1 r9). FY25 10-K, Note 10: ¶12 (up to $2.3bn; quarterly installments; final payment 3/28/2028), ¶16 (security), ¶18 (unconditional parent guarantee), ¶9 (SOFR/ABR + spread). Draw period ended (amortizing). | T2: Closed | U2: 0 | V2: =IF(C2="Subsequent event",0,IF(ISNUMBER(T2),IF(T2>=$B$25,H2-I2-U2,0),0)) | W2: =K2*O2 | X2: =YEAR(P2)
A3: DDTL 2.0 Facility | B3: DDTL | C3: Reported 6/30 | D3: Subsidiary (not named in filings used) | E3: Recourse | F3: Secured | G3: Full | H3: 7600 | I3: ='10Q_Debt'!D10 | J3: 0 | K3: =I3+J3 | L3: =IF(ISNUMBER(T3),IF(T3>=$B$24,H3-K3-U3,0),0) | M3: Floating | N3: SOFR or ABR + spread (spread not disclosed) | O3: ='10Q_Debt'!C10 | P3: 47726 | Q3: Amortizing | R3: Subsidiary equity + substantially all subsidiary assets (GPU servers); related customer contracts (10Q ¶30) | S3: Q2'26 10-Q, Note 10, p.27 (T1 r10). FY25 10-K, Note 10: ¶13 (up to $7.6bn; quarterly from Jan 2026; final payment 5 yrs after each loan funded), ¶16, ¶18. Draw period not stated; balance amortizing (5,037 -> 3,190), treated as closed. | T3: Closed | U3: 0 | V3: =IF(C3="Subsequent event",0,IF(ISNUMBER(T3),IF(T3>=$B$25,H3-I3-U3,0),0)) | W3: =K3*O3 | X3: =YEAR(P3)
A4: DDTL 2.1 Facility | B4: DDTL | C4: Reported 6/30 | D4: Same subsidiary as DDTL 2.0 (new tranche) | E4: Recourse | F4: Secured | G4: Full | H4: 3000 | I4: ='10Q_Debt'!D11 | J4: 0 | K4: =I4+J4 | L4: =IF(ISNUMBER(T4),IF(T4>=$B$24,H4-K4-U4,0),0) | M4: Floating | N4: SOFR or ABR + spread (spread not disclosed) | O4: ='10Q_Debt'!C11 | P4: 47938 | Q4: Amortizing | R4: Subsidiary equity + substantially all subsidiary assets (GPU servers); related customer contracts (10Q ¶30) | S4: Q2'26 10-Q, Note 10, p.27 (T1 r11). FY25 10-K, Note 10: ¶15 (tranche up to $3.0bn added to DDTL 2.0, drawable through Mar 2026; quarterly from Jul 2026; final 5 yrs after funding), ¶16, ¶18. | T4: 46112 | U4: 0 | V4: =IF(C4="Subsequent event",0,IF(ISNUMBER(T4),IF(T4>=$B$25,H4-I4-U4,0),0)) | W4: =K4*O4 | X4: =YEAR(P4)
A5: DDTL 3.0 Facility | B5: DDTL | C5: Reported 6/30 | D5: Subsidiary (not named in filings used) | E5: Recourse | F5: Secured | G5: Full | H5: 2600 | I5: ='10Q_Debt'!D12 | J5: 0 | K5: =I5+J5 | L5: =IF(ISNUMBER(T5),IF(T5>=$B$24,H5-K5-U5,0),0) | M5: Floating | N5: SOFR or ABR + spread (spread not disclosed); >=75% swapped | O5: ='10Q_Debt'!C12 | P5: 47726 | Q5: Amortizing | R5: Subsidiary equity + substantially all subsidiary assets (GPU servers); related customer contracts (10Q ¶30) | S5: Q2'26 10-Q, Note 10, p.27 (T1 r12). FY25 10-K, Note 10: ¶14 (up to $2.6bn, drawable through Jul 2026; monthly from Apr 2026; final Aug 2030; swaps >=75%), ¶16, ¶18. Available at 6/30, closed by 8/13. | T5: 46234 | U5: 0 | V5: =IF(C5="Subsequent event",0,IF(ISNUMBER(T5),IF(T5>=$B$25,H5-I5-U5,0),0)) | W5: =K5*O5 | X5: =YEAR(P5)
A6: DDTL 5.0 Facility | B6: DDTL | C6: Reported 6/30 | D6: CoreWeave Financing DDTL V, LLC (CFD V) | E6: Recourse | F6: Secured | G6: Full | H6: ='10Q_Debt'!D41 | I6: ='10Q_Debt'!D13 | J6: 0 | K6: =I6+J6 | L6: =IF(ISNUMBER(T6),IF(T6>=$B$24,H6-K6-U6,0),0) | M6: Floating | N6: SOFR + 4.50% | O6: ='10Q_Debt'!C13 | P6: 48182 | Q6: Amortizing | R6: Subsidiary equity + substantially all subsidiary assets (GPU servers); related customer contracts (10Q ¶30) | S6: Q2'26 10-Q, Note 10, pp.27-30 (T1 r13, T2 r41); ¶24 (borrower, $3.1bn, draw to 9/30/26, monthly from Nov 2026), ¶25 (security), ¶27 (parent guarantee), ¶30. Maturity per T1 = Nov 2031; ¶24 says expected final payment May 2031 (inconsistent). No post-6/30 draws disclosed. | T6: 46295 | U6: 0 | V6: =IF(C6="Subsequent event",0,IF(ISNUMBER(T6),IF(T6>=$B$25,H6-I6-U6,0),0)) | W6: =K6*O6 | X6: =YEAR(P6)
A7: 2030 Senior Notes | B7: Senior Notes | C7: Reported 6/30 | D7: CoreWeave, Inc. (Parent) | E7: Recourse | F7: Unsecured | G7: N/A | H7: ='10Q_Debt'!D14 | I7: ='10Q_Debt'!D14 | J7: 0 | K7: =I7+J7 | L7: =IF(ISNUMBER(T7),IF(T7>=$B$24,H7-K7-U7,0),0) | M7: Fixed | N7: Not stated in filings used (effective ~10%) | O7: ='10Q_Debt'!C14 | P7: 47635 | Q7: Bullet | R7: None - general corporate credit | S7: Q2'26 10-Q, Note 10, p.27 (T1 r14). FY25 10-K, Note 10: ¶21 ($2.0bn issued May 2025, due 6/1/2030), ¶23 (unsecured; semi-annual interest). Coupon not stated in the 10-K/10-Q text. | T7: n/a | U7: 0 | V7: =IF(C7="Subsequent event",0,IF(ISNUMBER(T7),IF(T7>=$B$25,H7-I7-U7,0),0)) | W7: =K7*O7 | X7: =YEAR(P7)
A8: 2031 9.00% Senior Notes | B8: Senior Notes | C8: Reported 6/30 | D8: CoreWeave, Inc. (Parent) | E8: Recourse | F8: Unsecured | G8: N/A | H8: ='10Q_Debt'!D15 | I8: ='10Q_Debt'!D15 | J8: 0 | K8: =I8+J8 | L8: =IF(ISNUMBER(T8),IF(T8>=$B$24,H8-K8-U8,0),0) | M8: Fixed | N8: 9.00% | O8: ='10Q_Debt'!C15 | P8: 47880 | Q8: Bullet | R8: None - general corporate credit | S8: Q2'26 10-Q, Note 10, p.27 (T1 r15). FY25 10-K, Note 10: ¶22 (issued Jul 2025, due 2/1/2031; text '$1.8bn' is rounded, table 1,750), ¶23 (unsecured). | T8: n/a | U8: 0 | V8: =IF(C8="Subsequent event",0,IF(ISNUMBER(T8),IF(T8>=$B$25,H8-I8-U8,0),0)) | W8: =K8*O8 | X8: =YEAR(P8)
A9: 2031 9.75% Senior Notes | B9: Senior Notes | C9: Reported 6/30 | D9: CoreWeave, Inc. (Parent) | E9: Recourse | F9: Unsecured | G9: N/A | H9: ='10Q_Debt'!D42 | I9: ='10Q_Debt'!D16 | J9: 0 | K9: =I9+J9 | L9: =IF(ISNUMBER(T9),IF(T9>=$B$24,H9-K9-U9,0),0) | M9: Fixed | N9: 9.75% | O9: ='10Q_Debt'!C16 | P9: 48122 | Q9: Bullet | R9: None - general corporate credit | S9: Q2'26 10-Q, Note 10, pp.27-28, 31-32 (T1 r16, T2 r42); ¶48 (issued Apr 2026, due 10/1/2031; text '$2.8bn' rounded), ¶51 (unsecured; semi-annual interest). | T9: n/a | U9: 0 | V9: =IF(C9="Subsequent event",0,IF(ISNUMBER(T9),IF(T9>=$B$25,H9-I9-U9,0),0)) | W9: =K9*O9 | X9: =YEAR(P9)
A10: 2032 9.625% Senior Notes | B10: Senior Notes | C10: Reported 6/30 | D10: CoreWeave, Inc. (Parent) | E10: Recourse | F10: Unsecured | G10: N/A | H10: ='10Q_Debt'!D43 | I10: ='10Q_Debt'!D17 | J10: 0 | K10: =I10+J10 | L10: =IF(ISNUMBER(T10),IF(T10>=$B$24,H10-K10-U10,0),0) | M10: Fixed | N10: 9.625% | O10: ='10Q_Debt'!C17 | P10: 48410 | Q10: Bullet | R10: None - general corporate credit | S10: Q2'26 10-Q, Note 10, pp.27-28, 31-32 (T1 r17, T2 r43); ¶49 (issued Jun 2026, due 7/15/2032), ¶51 (unsecured). | T10: n/a | U10: 0 | V10: =IF(C10="Subsequent event",0,IF(ISNUMBER(T10),IF(T10>=$B$25,H10-I10-U10,0),0)) | W10: =K10*O10 | X10: =YEAR(P10)
A11: 2032 EUR Senior Notes | B11: Senior Notes | C11: Reported 6/30 | D11: CoreWeave, Inc. (Parent) | E11: Recourse | F11: Unsecured | G11: N/A | H11: ='10Q_Debt'!D18 | I11: ='10Q_Debt'!D18 | J11: 0 | K11: =I11+J11 | L11: =IF(ISNUMBER(T11),IF(T11>=$B$24,H11-K11-U11,0),0) | M11: Fixed | N11: 8.50% (EUR); cross-currency swapped | O11: ='10Q_Debt'!C18 | P11: 48410 | Q11: Bullet | R11: None - general corporate credit | S11: Q2'26 10-Q, Note 10, pp.27-28, 31-32 (T1 r18 = USD 2,279 at 6/30; T2 r44 = EUR 2,000 principal); ¶50 (due 7/15/2032), ¶51 (unsecured); T1 footnote (1) (cross-currency swaps, fair value hedge). Commitment shown in USD = principal. | T11: n/a | U11: 0 | V11: =IF(C11="Subsequent event",0,IF(ISNUMBER(T11),IF(T11>=$B$25,H11-I11-U11,0),0)) | W11: =K11*O11 | X11: =YEAR(P11)
A12: 2031 Convertible Senior Notes | B12: Convertible | C12: Reported 6/30 | D12: CoreWeave, Inc. (Parent) | E12: Recourse | F12: Unsecured | G12: N/A | H12: ='10Q_Debt'!D19 | I12: ='10Q_Debt'!D19 | J12: 0 | K12: =I12+J12 | L12: =IF(ISNUMBER(T12),IF(T12>=$B$24,H12-K12-U12,0),0) | M12: Fixed | N12: Not stated in filings used (effective ~2%) | O12: ='10Q_Debt'!C19 | P12: 48183 | Q12: Bullet | R12: None - general corporate credit; conversion price ~$107.80 | S12: Q2'26 10-Q, Note 10, p.27 (T1 r19). FY25 10-K, Note 10: ¶26 (issued Dec 2025, due 12/1/2031; text '$2.6bn' rounded), ¶27 (conversion ~$107.80), ¶30 (unsecured). Coupon not stated in the text. | T12: n/a | U12: 0 | V12: =IF(C12="Subsequent event",0,IF(ISNUMBER(T12),IF(T12>=$B$25,H12-I12-U12,0),0)) | W12: =K12*O12 | X12: =YEAR(P12)
A13: 2032 Convertible Senior Notes | B13: Convertible | C13: Reported 6/30 | D13: CoreWeave, Inc. (Parent) | E13: Recourse | F13: Unsecured | G13: N/A | H13: ='10Q_Debt'!D45 | I13: ='10Q_Debt'!D20 | J13: 0 | K13: =I13+J13 | L13: =IF(ISNUMBER(T13),IF(T13>=$B$24,H13-K13-U13,0),0) | M13: Fixed | N13: 1.75% | O13: ='10Q_Debt'!C20 | P13: 48488 | Q13: Bullet | R13: None - general corporate credit; conversion price ~$119.60 | S13: Q2'26 10-Q, Note 10, pp.27-28, 30-31 (T1 r20, T2 r45); ¶37 (issued Apr 2026, due 10/1/2032), ¶38 (conversion ~$119.60), ¶42 (unsecured). | T13: n/a | U13: 0 | V13: =IF(C13="Subsequent event",0,IF(ISNUMBER(T13),IF(T13>=$B$25,H13-I13-U13,0),0)) | W13: =K13*O13 | X13: =YEAR(P13)
A14: Convertible Promissory Notes | B14: Other | C14: Reported 6/30 | D14: CoreWeave, Inc. (Parent) | E14: Recourse | F14: Not disclosed | G14: N/A | H14: 172 | I14: ='10Q_Debt'!D21 | J14: 0 | K14: =I14+J14 | L14: =IF(ISNUMBER(T14),IF(T14>=$B$24,H14-K14-U14,0),0) | M14: Fixed | N14: 0% (non-interest-bearing; 7% imputed) | O14: ='10Q_Debt'!C21 | P14: 46142 | Q14: Bullet | R14: None - settled in Class A shares in Apr 2026 | S14: Q2'26 10-Q, Note 10, pp.27, 32 (T1 r21 = 0 at 6/30); ¶56 (settled in shares Apr 2026). FY25 10-K, Note 10: ¶51 ($172mm principal, matures Apr 2026), ¶53 (7% imputed rate). Kept for 1:1 tie-out with T1. | T14: n/a | U14: 0 | V14: =IF(C14="Subsequent event",0,IF(ISNUMBER(T14),IF(T14>=$B$25,H14-I14-U14,0),0)) | W14: =K14*O14 | X14: =YEAR(P14)
A15: Revolving Credit Facility | B15: Revolver | C15: Reported 6/30 | D15: CoreWeave, Inc. (Parent) | E15: Recourse | F15: Secured | G15: N/A | H15: 2500 | I15: ='10Q_Debt'!D22 | J15: 1200 | K15: =I15+J15 | L15: =IF(ISNUMBER(T15),IF(T15>=$B$24,H15-K15-U15,0),0) | M15: Floating | N15: Spread not disclosed in filings used | O15: ='10Q_Debt'!C22 | P15: 47452 | Q15: Revolving | R15: Pledges of certain assets (not specified) | S15: Q2'26 10-Q, Note 10, pp.27, 30 (T1 r22); ¶32 (LCs $533mm reduce availability), ¶33 (repaid Apr 2026; $2.0bn available at 6/30; secured; 0.25% undrawn fee). FY25 10-K, Note 10: ¶39 ($2.5bn; matures Nov 2029). Subsequent: Note 16 ($1.2bn drawn Aug 2026). LCs assumed unchanged at 8/13. | T15: 47452 | U15: 533 | V15: =IF(C15="Subsequent event",0,IF(ISNUMBER(T15),IF(T15>=$B$25,H15-I15-U15,0),0)) | W15: =K15*O15 | X15: =YEAR(P15)
A16: OEM and Software License Financing Arrangements (recourse) | B16: Vendor Financing | C16: Reported 6/30 | D16: Not specified (Company) | E16: Recourse | F16: Secured | G16: Not disclosed | H16: ='10Q_Debt'!D23 | I16: ='10Q_Debt'!D23 | J16: 0 | K16: =I16+J16 | L16: =IF(ISNUMBER(T16),IF(T16>=$B$24,H16-K16-U16,0),0) | M16: Not disclosed | N16: Not disclosed | O16: ='10Q_Debt'!C23 | P16: 47695 | Q16: Not disclosed | R16: Financed equipment | S16: Q2'26 10-Q, Note 10, pp.27, 30 (T1 r23: maturities Dec 2026 - Jul 2030; latest used); ¶35 (OEM $4.8bn + software $347mm, recourse + non-recourse combined). FY25 10-K, Note 10: ¶42 (security interest in financed equipment; terms 1-3 yrs), ¶43-44 (optional $884mm software tranche not committed, not recognized). | T16: n/a | U16: 0 | V16: =IF(C16="Subsequent event",0,IF(ISNUMBER(T16),IF(T16>=$B$25,H16-I16-U16,0),0)) | W16: =K16*O16 | X16: =YEAR(P16)
A17: Magnetar Loan | B17: Other | C17: Reported 6/30 | D17: CoreWeave, Inc. (Parent) | E17: Recourse | F17: Not disclosed | G17: N/A | H17: ='10Q_Debt'!D24 | I17: ='10Q_Debt'!D24 | J17: 0 | K17: =I17+J17 | L17: =IF(ISNUMBER(T17),IF(T17>=$B$24,H17-K17-U17,0),0) | M17: Fixed | N17: 12% annual return (redemption premium accretion) | O17: ='10Q_Debt'!C24 | P17: 47149 | Q17: Bullet | R17: None disclosed - refundable customer deposit treated as debt | S17: Q2'26 10-Q, Note 10, pp.27, 32 (T1 r24); ¶54 ($100mm partial settlement Jun 2026; $189mm remaining incl. accrued premium). FY25 10-K, Note 10: ¶46-49 ($230mm refundable deposit; in-substance debt; 12% annual return on refund). | T17: n/a | U17: 0 | V17: =IF(C17="Subsequent event",0,IF(ISNUMBER(T17),IF(T17>=$B$25,H17-I17-U17,0),0)) | W17: =K17*O17 | X17: =YEAR(P17)
A18: DDTL 4.0 Facility | B18: DDTL | C18: Reported 6/30 | D18: CoreWeave Compute Acquisition Co. VIII, LLC (CCAC VIII) | E18: Non-recourse | F18: Secured | G18: Carve-outs only | H18: ='10Q_Debt'!D40 | I18: ='10Q_Debt'!D30 | J18: 0 | K18: =I18+J18 | L18: =IF(ISNUMBER(T18),IF(T18>=$B$24,H18-K18-U18,0),0) | M18: Mixed | N18: SOFR + 2.25% ($1.4bn); Treasury + 2.00% fixed ($1.5bn) | O18: ='10Q_Debt'!C30 | P18: 48304 | Q18: Amortizing | R18: CCAC VIII equity + substantially all CCAC VIII assets (compute infrastructure; $3.3bn non-current + $155mm current at 6/30); related customer contracts (10Q ¶30) | S18: Q2'26 10-Q, Note 10, pp.27-29 (T1 r30, T2 r40); ¶16 (borrower, $8.5bn, draw to 6/30/27, floating/fixed split), ¶17 (monthly amortization; balance at maturity), ¶18 (use), ¶21 (security; non-recourse except carve-outs), ¶30. No post-6/30 draws disclosed. | T18: 46568 | U18: 0 | V18: =IF(C18="Subsequent event",0,IF(ISNUMBER(T18),IF(T18>=$B$25,H18-I18-U18,0),0)) | W18: =K18*O18 | X18: =YEAR(P18)
A19: OEM and Software License Financing Arrangements (non-recourse) | B19: Vendor Financing | C19: Reported 6/30 | D19: Not specified (subsidiary) | E19: Non-recourse | F19: Secured | G19: Carve-outs only | H19: ='10Q_Debt'!D31 | I19: ='10Q_Debt'!D31 | J19: 0 | K19: =I19+J19 | L19: =IF(ISNUMBER(T19),IF(T19>=$B$24,H19-K19-U19,0),0) | M19: Not disclosed | N19: Not disclosed | O19: ='10Q_Debt'!C31 | P19: 46996 | Q19: Not disclosed | R19: Financed equipment | S19: Q2'26 10-Q, Note 10, p.27 (T1 r31: maturities Aug 2026 - Aug 2028; latest used); ¶5 (non-recourse definition: carve-out guarantees only). FY25 10-K, Note 10: ¶42 (security interest in financed equipment). | T19: n/a | U19: 0 | V19: =IF(C19="Subsequent event",0,IF(ISNUMBER(T19),IF(T19>=$B$25,H19-I19-U19,0),0)) | W19: =K19*O19 | X19: =YEAR(P19)
A20: DDTL 5.5 Facility | B20: DDTL | C20: Subsequent event | D20: CoreWeave Financing DDTL V-V, LLC | E20: Recourse | F20: Secured | G20: Full | H20: 2600 | I20: 0 | J20: 1200 | K20: =I20+J20 | L20: =IF(ISNUMBER(T20),IF(T20>=$B$24,H20-K20-U20,0),0) | M20: Floating | N20: Term SOFR + 5.50% (0% floor); ABR + 4.50% | O20: n/a (new) | P20: 48092 | Q20: Not disclosed | R20: All borrower and subsidiary assets + 100% equity pledge (Holdco); customer contracts avg ~3 yrs vs ~5-yr loan | S20: Subsequent tab: A1 (Note 16: $2.6bn, matures Sep 2031, $1.2bn drawn), B1-B4 (8-K Item 1.01: closed 8/7/26; draw to Dec 2026; maturity 9/1/2031; Term SOFR + 5.50%; parent guarantee + security), B6 (DSCR >= 1.35x), C3/C8 (PR: ~3-yr contracts; Ba2/BB+). | T20: 46387 | U20: 0 | V20: =IF(C20="Subsequent event",0,IF(ISNUMBER(T20),IF(T20>=$B$25,H20-I20-U20,0),0)) | W20: =K20*$B$26 | X20: =YEAR(P20)
A21: Total | I21: =SUM(I2:I20) | J21: =SUM(J2:J20) | K21: =SUM(K2:K20) | L21: =SUM(L2:L20) | V21: =SUM(V2:V20) | W21: =SUM(W2:W20)
V22: Weighted avg rate | W22: =W21/K21
A23: Inputs
A24: Analysis date (Undrawn 8/13 uses this) | B24: 46247
A25: Balance sheet date (Undrawn 6/30 uses this) | B25: 46203
A26: DDTL 5.5 assumed effective rate | B26: 0.1 | C26: Assumption: DDTL 5.0 (SOFR + 4.50%) effective rate 9% in the 10-Q; DDTL 5.5 is SOFR + 5.50% -> ~10%
A27: Legend
A28: Blue = typed from a source (cited in column S); Green = link to another tab; Black = formula.
A29: Undrawn = Commitment - Principal - Availability Reductions, only while the draw period is open (Draw Period End on/after the date). 'Closed' / 'n/a' = 0. Undrawn 6/30 excludes facilities signed after 6/30.
A30: Pro forma 8/13 = 6/30 principal + draws disclosed after 6/30 (10-Q Note 16 / 8-K). Scheduled repayments after 6/30 are not disclosed and not deducted.
A31: Allowed values - Type: DDTL / Senior Notes / Convertible / Revolver / Vendor Financing / Other. Status: Reported 6/30 / Subsequent event. Recourse: Recourse / Non-recourse.
A32: Secured: Secured / Unsecured / Not disclosed. Parent Guarantee: Full / Carve-outs only / N/A (borrower is the parent) / Not disclosed. Amortizing/Bullet: Amortizing / Bullet / Revolving / Not disclosed.
A34: Checks (should all be 0)
A35: Principal 6/30 total vs 10-Q maturity schedule total (10Q_Debt T3) | B35: =I21-'10Q_Debt'!B57
A36: Recourse principal vs 10-Q (total recourse net + discount) | B36: =SUMIF(E2:E20,"Recourse",I2:I20)-('10Q_Debt'!D26-'10Q_Debt'!D25)
A37: Non-recourse principal vs 10-Q (total non-recourse net + discount) | B37: =SUMIF(E2:E20,"Non-recourse",I2:I20)-('10Q_Debt'!D33-'10Q_Debt'!D32)
A38: Undrawn 6/30 total vs MD&A 'Availability under existing facilities' | B38: =V21-'10Q_Debt'!B72
A39: Pro forma = 6/30 principal + subsequent draws | B39: =K21-I21-J21
A40: Logic: Non-recourse rows with a Full parent guarantee (count) | B40: =COUNTIFS(E2:E20,"Non-recourse",G2:G20,"Full")
A41: Logic: Recourse rows with Carve-outs only (count) | B41: =COUNTIFS(E2:E20,"Recourse",G2:G20,"Carve-outs only")
A43: Summary - pro forma principal at 8/13 ($mm) | B43: Pro forma | C43: % of total
A44: By recourse
A45: Recourse | B45: =SUMIF(E2:E20,"Recourse",K2:K20) | C45: =IF($K$21=0,0,B45/$K$21)
A46: Non-recourse | B46: =SUMIF(E2:E20,"Non-recourse",K2:K20) | C46: =IF($K$21=0,0,B46/$K$21)
A47: By security
A48: Secured | B48: =SUMIF(F2:F20,"Secured",K2:K20) | C48: =IF($K$21=0,0,B48/$K$21)
A49: Unsecured | B49: =SUMIF(F2:F20,"Unsecured",K2:K20) | C49: =IF($K$21=0,0,B49/$K$21)
A50: Not disclosed | B50: =SUMIF(F2:F20,"Not disclosed",K2:K20) | C50: =IF($K$21=0,0,B50/$K$21)
A51: By rate type
A52: Fixed | B52: =SUMIF(M2:M20,"Fixed",K2:K20) | C52: =IF($K$21=0,0,B52/$K$21)
A53: Floating | B53: =SUMIF(M2:M20,"Floating",K2:K20) | C53: =IF($K$21=0,0,B53/$K$21)
A54: Mixed | B54: =SUMIF(M2:M20,"Mixed",K2:K20) | C54: =IF($K$21=0,0,B54/$K$21)
A55: Not disclosed | B55: =SUMIF(M2:M20,"Not disclosed",K2:K20) | C55: =IF($K$21=0,0,B55/$K$21)
A56: By type
A57: DDTL | B57: =SUMIF(B2:B20,"DDTL",K2:K20) | C57: =IF($K$21=0,0,B57/$K$21)
A58: Senior Notes | B58: =SUMIF(B2:B20,"Senior Notes",K2:K20) | C58: =IF($K$21=0,0,B58/$K$21)
A59: Convertible | B59: =SUMIF(B2:B20,"Convertible",K2:K20) | C59: =IF($K$21=0,0,B59/$K$21)
A60: Revolver | B60: =SUMIF(B2:B20,"Revolver",K2:K20) | C60: =IF($K$21=0,0,B60/$K$21)
A61: Vendor Financing | B61: =SUMIF(B2:B20,"Vendor Financing",K2:K20) | C61: =IF($K$21=0,0,B61/$K$21)
A62: Other | B62: =SUMIF(B2:B20,"Other",K2:K20) | C62: =IF($K$21=0,0,B62/$K$21)

Sheet Funding Need
A1: Funding Need - 2H26 and FY27 ($mm)
A2: Analysis date 2026-08-13. 2H26 = Jul-Dec 2026. Capex on the company’s definition. Base case: includes a minimum cash balance and interest on new debt (closed-form, no circular reference).
A3: ="Active scenario: "&Scenarios!C5
A4: ($mm) | B4: 2H26 | C4: FY27 | D4: Total | E4: Source / Note
A5: Uses of cash
A6: Capex (company basis) | B6: =B33 | C6: =C33 | D6: =B6+C6 | E6: See capex calc below
A7: Scheduled debt maturities | B7: ='10Q_Debt'!B51 | C7: ='10Q_Debt'!B52 | D7: =B7+C7 | E7: 10-Q Note 10, Table 3 (principal due; 6/30 debt only)
A8: Interest on existing debt and facility draws | B8: =B44 | C8: =C44 | D8: =B8+C8 | E8: See interest calc below
A9: Minimum cash balance | B9: 2000 | C9: 0 | D9: =B9+C9 | E9: Assumption: ~1 quarter of cash operating costs (2H26 revenue x (1 - EBITDA margin) / 2 = ~1,740), rounded up to 2,000. Kept from 2H26 onward; not counted again in FY27
A10: Total uses | B10: =SUM(B6:B9) | C10: =SUM(C6:C9) | D10: =SUM(D6:D9)
A12: Sources of cash
A13: Pro forma cash (8/13) | B13: =B50 | D13: =B13 | E13: See liquidity calc below; excludes restricted cash
A14: Undrawn committed facilities (8/13) | B14: ='Debt Database'!L21 | D14: =B14 | E14: DDTL draws restricted to capex; unused amounts expire at draw-period end
A15: Operating cash flow before interest | B15: =B63 | C15: =C63 | D15: =B15+C15 | E15: See operating cash flow calc below
A16: Carryover from prior period | C16: =MAX(B17-B10,0) | E16: Unused 2H26 sources roll into FY27; not added in Total (already counted)
A17: Total sources | B17: =SUM(B13:B16) | C17: =SUM(C13:C16) | D17: =SUM(D13:D15)
A19: Funding gap before new-debt interest | B19: =MAX(B10-B17,0) | C19: =MAX(C10-C17,0) | D19: =B19+C19 | E19: Includes minimum cash; before interest on new debt
A21: New debt interest rate | B21: =Scenarios!$F$12 | C21: =B21 | E21: Active scenario (Scenarios F12); base 9.5% - rationale on Scenarios tab
A22: Interest on prior-period new debt | B22: 0 | C22: =B24*C21*1 | E22: 2H26 new debt is outstanding all of FY27 (assumed bullet: no repayment before 2028)
A23: Timing factor (avg outstanding) | B23: 0.25 | C23: 0.5 | E23: Borrowed evenly through the period, so outstanding half the time on average: 2H26 = 0.5 yr x 0.5; FY27 = 1 yr x 0.5
A24: New financing required | B24: =(B19+B22)/(1-B21*B23) | C24: =(C19+C22)/(1-C21*C23) | D24: =B24+C24 | E24: N = (gap + interest on prior-period new debt) / (1 - rate x timing). Solves N = gap + interest on N without a circular reference
A25: Memo: interest on new debt | B25: =B24*B21*B23+B22 | C25: =C24*C21*C23+C22 | D25: =B25+C25 | E25: Not added to Uses (that would be circular); already funded inside row 24
A27: Supporting calculations
A28: Capex
A29: FY26 capex guidance - low | B29: 35000 | E29: ="Guidance!E9: "&Guidance!E9
A30: FY26 capex guidance - high | B30: 39000
A31: FY26 capex - midpoint | B31: =AVERAGE(B29,B30)
A32: Less: 1H26 capex (company basis) | B32: =Guidance!E19 | E32: Earnings Presentation slide 16
A33: Capex | B33: =B31-B32 | C33: 37000 | E33: FY27 assumption: flat at FY26 guidance midpoint
A35: Interest on existing debt and facility draws
A36: Opening debt (pro forma principal) | B36: ='Debt Database'!K21 | C36: =B38 | E36: 2H26 opens at 8/13 pro forma; FY27 opens at 2H26 closing
A37: Less: scheduled maturities | B37: =-B7 | C37: =-C7
A38: Closing debt | B38: =B36+B37 | C38: =C36+C37
A39: Average debt | B39: =AVERAGE(B36,B38) | C39: =AVERAGE(C36,C38) | E39: Assumes repayments spread evenly through the period
A40: Weighted average effective rate | B40: ='Debt Database'!W22 | C40: =B40 | E40: Debt Database W22; 10-Q effective rates (rounded to whole %)
A41: Year fraction | B41: 0.5 | C41: 1
A42: SOFR shock on floating-rate debt | B42: ='Debt Database'!$B$53*Scenarios!$F$11/10000*B41 | C42: ='Debt Database'!$B$53*Scenarios!$F$11/10000*C41 | E42: Floating-rate debt (Debt Database B53, ~13.2bn) x shock (bp / 10,000) x year fraction; 0 in Base
A43: Interest on draws of committed facilities | B43: =B14*B40*B23 | C43: =B14*C40*C41 | E43: Undrawn facilities used as a source become debt: drawn evenly in 2H26 (avg 0.25 yr), outstanding all of FY27; at weighted avg effective rate
A44: Interest on existing debt and facility draws | B44: =B39*B40*B41+B42+B43 | C44: =C39*C40*C41+C42+C43
A46: Pro forma cash
A47: Cash and cash equivalents (6/30) | B47: ='10Q_Debt'!B70 | E47: 10-Q MD&A liquidity table; restricted cash excluded
A48: Marketable securities (6/30) | B48: ='10Q_Debt'!B71
A49: Add: draws after 6/30 | B49: ='Debt Database'!J21 | E49: Aug 2026: revolver 1,200 + DDTL 5.5 1,200 (debt side already in opening debt)
A50: Pro forma cash (8/13) | B50: =SUM(B47:B49)
A52: Operating cash flow before interest
A53: FY26 revenue guidance - low | B53: 12400 | E53: ="Guidance!E7: "&Guidance!E7
A54: FY26 revenue guidance - high | B54: 13200
A55: FY26 revenue - midpoint | B55: =AVERAGE(B53,B54)
A56: Less: 1H26 revenue | B56: ='PR_Q2-26'!D18 | E56: Q2'26 press release, six months 2026
A57: Revenue before scenario adjustment | B57: =B55-B56 | C57: 19000 | E57: ="FY27 = exiting 2026 ARR midpoint (no growth). Guidance!E10: "&Guidance!E10
A58: Scenario adjustment (% chg) | B58: =Scenarios!$F$8 | C58: =Scenarios!$F$9 | E58: Active scenario (Scenarios F8:F9); 0% in Base
A59: Revenue | B59: =B57*(1+B58) | C59: =C57*(1+C58)
A60: Adj. EBITDA margin | B60: =Scenarios!$F$10 | C60: =B60 | E60: Active scenario (Scenarios F10); base = 1H26 actual (2,667 / 4,653); FY27 held flat
A61: Adj. EBITDA | B61: =B59*B60 | C61: =C59*C60
A62: Less: cash taxes / working capital | B62: 0 | C62: 0 | E62: Assumed nil: loss-making (low cash tax); customer prepayments ignored (conservative)
A63: Operating cash flow before interest | B63: =B61-B62 | C63: =C61-C62
A65: Checks (should be 0)
A66: Total funding gap vs total uses - total sources | D66: =D19-(D10-D17)
A67: Liquidity links vs 10-Q MD&A total liquidity (6/30) | D67: =(B47+B48+'Debt Database'!V21)-'10Q_Debt'!B73
A68: New financing = funding gap + interest on new debt | D68: =D24-(D19+D25)
A70: Memo: interest cross-check vs company guidance (not used in the model)
A71: Q3'26 interest expense guidance - low | B71: 860 | E71: ="Guidance!B9: "&Guidance!B9
A72: Q3'26 interest expense guidance - high | B72: 940
A73: Implied 2H26 interest (Q3 midpoint x 2) | B73: =AVERAGE(B71,B72)*2
A74: Difference vs model (existing + new debt) | B74: =B73-B8-B25 | E74: Model now slightly above guidance-implied 2H26 interest (conservative): facility draws and new debt assumed to start 7/1

Sheet Metrics
A1: Credit Metrics ($mm)
A2: LTM = FY25 + 1H26 - 1H25 Debt pro forma 8/13; earnings LTM to 6/30/2026
B3: FY25 | C3: 1H26 | D3: 1H25 | E3: LTM | F3: Q2'26 | G3: Run-rate | H3: Source/Note
A4: Financials
A5: Revenue | B5: ='PR_Q4-25'!D18 | C5: ='PR_Q2-26'!D18 | D5: ='PR_Q2-26'!E18 | E5: =B5+C5-D5 | F5: ='PR_Q2-26'!B18 | G5: =F5*4
A6: Adj. EBITDA | B6: ='PR_Q4-25'!D17 | C6: ='PR_Q2-26'!D17 | D6: ='PR_Q2-26'!E17 | E6: =B6+C6-D6 | F6: ='PR_Q2-26'!B17 | G6: =F6*4
A7: D&A | B7: ='PR_Q4-25'!D10 | C7: ='PR_Q2-26'!D10 | D7: ='PR_Q2-26'!E10 | E7: =B7+C7-D7 | F7: ='PR_Q2-26'!B10 | G7: =F7*4
A8: Adj. operating income | B8: ='PR_Q4-25'!D31 | C8: ='PR_Q2-26'!D31 | D8: ='PR_Q2-26'!E31 | E8: =B8+C8-D8 | F8: ='PR_Q2-26'!B31 | G8: =F8*4
A9: Interest expense, net | B9: ='PR_Q4-25'!D11 | C9: ='PR_Q2-26'!D11 | D9: ='PR_Q2-26'!E11 | E9: =B9+C9-D9 | F9: ='PR_Q2-26'!B11 | G9: =F9*4 | H9: Net of interest income
A11: Debt (pro forma 8/13)
A12: Total debt (principal) | E12: ='Debt Database'!K21 | H12: Debt Database K21; principal, pro forma 8/13
A13: Recourse debt | E13: ='Debt Database'!B45 | H13: Debt Database B45; incl. Aug revolver and DDTL 5.5 draws
A14: Less: pro forma cash | E14: ='Funding Need'!B13 | H14: Funding Need B13; excludes restricted cash
A15: Net debt | E15: =E12-E14
A17: Credit ratios
A18: Total debt / Adj. EBITDA | E18: =E12/E6 | G18: =E12/G6 | H18: Debt at 8/13 vs LTM EBITDA to 6/30
A19: Net debt / Adj. EBITDA | E19: =E15/E6 | G19: =E15/G6
A20: Recourse debt / Adj. EBITDA | E20: =E13/E6 | G20: =E13/G6
A21: Adj. EBITDA / interest | E21: =E6/E9 | G21: =G6/G9
A22: Adj. operating income / interest | E22: =E8/E9 | G22: =G8/G9 | H22: operating profit covers ~1/4 of interest
A23: Adj. EBITDA / pro forma interest | G23: =G6/'Debt Database'!W21 | H23: Pro forma interest = 8/13 debt x 10-Q effective rates (Debt Database W21)
A24: Adj. operating income / pro forma interest | G24: =G8/'Debt Database'!W21
A26: Liquidity (pro forma 8/13)
A27: Pro forma cash | E27: ='Funding Need'!B13 | H27: Excludes restricted cash
A28: Undrawn revolver | E28: ='Debt Database'!L15 | H28: General corporate purposes; net of 533 letters of credit
A29: Undrawn DDTLs | E29: ='Debt Database'!L21-E28 | H29: Capex on specific contracts only; cannot fund debt service
A30: Total liquidity | E30: =SUM(E27:E29) | H30: Ties to Funding Need B13 + B14
A31: Principal due within 12 months | E31: =-('10Q_Debt'!D27+'10Q_Debt'!D34) | H31: 10-Q current portion of debt (6/30); cross-check Table 3: 4,413 + 6,184/2 = 7,505
A32: Pro forma annual interest | E32: ='Debt Database'!W21 | H32: 8/13 debt x 10-Q effective rates
A33: NTM debt service | E33: =E31+E32
A34: Total liquidity / NTM debt service | E34: =E30/E33
A35: Cash + revolver NTM debt service | E35: =(E27+E28)/E33 | H35: Excludes capex-only DDTL availability

Sheet Maturity
A1: Maturity
A4: ($mm) | B4: 2H26 | C4: 2027 | D4: 2028 | E4: 2029 | F4: 2030 | G4: Thereafter | H4: Total | I4: Notes
A5: 10-Q scheduled principal (6/30) | B5: ='10Q_Debt'!$B51 | C5: ='10Q_Debt'!$B52 | D5: ='10Q_Debt'!$B53 | E5: ='10Q_Debt'!$B54 | F5: ='10Q_Debt'!$B55 | G5: ='10Q_Debt'!$B56 | H5: =SUM(B5:G5)
A6: Add: Aug revolver draw | E6: ='Debt Database'!J15 | H6: =SUM(B6:G6)
A7: Add: DDTL 5.5 draw | G7: ='Debt Database'!J20 | H7: =SUM(B7:G7) | I7: Amortization schedule not disclosed; placed at final maturity
A8: Pro forma total | B8: =SUM(B5:B7) | C8: =SUM(C5:C7) | D8: =SUM(D5:D7) | E8: =SUM(E5:E7) | F8: =SUM(F5:F7) | G8: =SUM(G5:G7) | H8: =SUM(B8:G8)
A9: % of total | B9: =B8/$H$8 | C9: =C8/$H$8 | D9: =D8/$H$8 | E9: =E8/$H$8 | F9: =F8/$H$8 | G9: =G8/$H$8
A10: Check (should be 0) | H10: =(H5-'10Q_Debt'!B57)+(H8-'Debt Database'!K21)
A12: By final maturity year (refinancing view, $mm)
B13: 2026 | C13: 2027 | D13: 2028 | E13: 2029 | F13: 2030 | G13: 2031 | H13: 2032 | I13: Total | J13: Notes
A14: DDTL | B14: =SUMIFS('Debt Database'!$K$2:$K$20,'Debt Database'!$B$2:$B$20,$A14,'Debt Database'!$X$2:$X$20,B$13) | C14: =SUMIFS('Debt Database'!$K$2:$K$20,'Debt Database'!$B$2:$B$20,$A14,'Debt Database'!$X$2:$X$20,C$13) | D14: =SUMIFS('Debt Database'!$K$2:$K$20,'Debt Database'!$B$2:$B$20,$A14,'Debt Database'!$X$2:$X$20,D$13) | E14: =SUMIFS('Debt Database'!$K$2:$K$20,'Debt Database'!$B$2:$B$20,$A14,'Debt Database'!$X$2:$X$20,E$13) | F14: =SUMIFS('Debt Database'!$K$2:$K$20,'Debt Database'!$B$2:$B$20,$A14,'Debt Database'!$X$2:$X$20,F$13) | G14: =SUMIFS('Debt Database'!$K$2:$K$20,'Debt Database'!$B$2:$B$20,$A14,'Debt Database'!$X$2:$X$20,G$13) | H14: =SUMIFS('Debt Database'!$K$2:$K$20,'Debt Database'!$B$2:$B$20,$A14,'Debt Database'!$X$2:$X$20,H$13) | I14: =SUM(B14:H14)
A15: Senior Notes | B15: =SUMIFS('Debt Database'!$K$2:$K$20,'Debt Database'!$B$2:$B$20,$A15,'Debt Database'!$X$2:$X$20,B$13) | C15: =SUMIFS('Debt Database'!$K$2:$K$20,'Debt Database'!$B$2:$B$20,$A15,'Debt Database'!$X$2:$X$20,C$13) | D15: =SUMIFS('Debt Database'!$K$2:$K$20,'Debt Database'!$B$2:$B$20,$A15,'Debt Database'!$X$2:$X$20,D$13) | E15: =SUMIFS('Debt Database'!$K$2:$K$20,'Debt Database'!$B$2:$B$20,$A15,'Debt Database'!$X$2:$X$20,E$13) | F15: =SUMIFS('Debt Database'!$K$2:$K$20,'Debt Database'!$B$2:$B$20,$A15,'Debt Database'!$X$2:$X$20,F$13) | G15: =SUMIFS('Debt Database'!$K$2:$K$20,'Debt Database'!$B$2:$B$20,$A15,'Debt Database'!$X$2:$X$20,G$13) | H15: =SUMIFS('Debt Database'!$K$2:$K$20,'Debt Database'!$B$2:$B$20,$A15,'Debt Database'!$X$2:$X$20,H$13) | I15: =SUM(B15:H15)
A16: Convertible | B16: =SUMIFS('Debt Database'!$K$2:$K$20,'Debt Database'!$B$2:$B$20,$A16,'Debt Database'!$X$2:$X$20,B$13) | C16: =SUMIFS('Debt Database'!$K$2:$K$20,'Debt Database'!$B$2:$B$20,$A16,'Debt Database'!$X$2:$X$20,C$13) | D16: =SUMIFS('Debt Database'!$K$2:$K$20,'Debt Database'!$B$2:$B$20,$A16,'Debt Database'!$X$2:$X$20,D$13) | E16: =SUMIFS('Debt Database'!$K$2:$K$20,'Debt Database'!$B$2:$B$20,$A16,'Debt Database'!$X$2:$X$20,E$13) | F16: =SUMIFS('Debt Database'!$K$2:$K$20,'Debt Database'!$B$2:$B$20,$A16,'Debt Database'!$X$2:$X$20,F$13) | G16: =SUMIFS('Debt Database'!$K$2:$K$20,'Debt Database'!$B$2:$B$20,$A16,'Debt Database'!$X$2:$X$20,G$13) | H16: =SUMIFS('Debt Database'!$K$2:$K$20,'Debt Database'!$B$2:$B$20,$A16,'Debt Database'!$X$2:$X$20,H$13) | I16: =SUM(B16:H16)
A17: Revolver | B17: =SUMIFS('Debt Database'!$K$2:$K$20,'Debt Database'!$B$2:$B$20,$A17,'Debt Database'!$X$2:$X$20,B$13) | C17: =SUMIFS('Debt Database'!$K$2:$K$20,'Debt Database'!$B$2:$B$20,$A17,'Debt Database'!$X$2:$X$20,C$13) | D17: =SUMIFS('Debt Database'!$K$2:$K$20,'Debt Database'!$B$2:$B$20,$A17,'Debt Database'!$X$2:$X$20,D$13) | E17: =SUMIFS('Debt Database'!$K$2:$K$20,'Debt Database'!$B$2:$B$20,$A17,'Debt Database'!$X$2:$X$20,E$13) | F17: =SUMIFS('Debt Database'!$K$2:$K$20,'Debt Database'!$B$2:$B$20,$A17,'Debt Database'!$X$2:$X$20,F$13) | G17: =SUMIFS('Debt Database'!$K$2:$K$20,'Debt Database'!$B$2:$B$20,$A17,'Debt Database'!$X$2:$X$20,G$13) | H17: =SUMIFS('Debt Database'!$K$2:$K$20,'Debt Database'!$B$2:$B$20,$A17,'Debt Database'!$X$2:$X$20,H$13) | I17: =SUM(B17:H17)
A18: Vendor Financing | B18: =SUMIFS('Debt Database'!$K$2:$K$20,'Debt Database'!$B$2:$B$20,$A18,'Debt Database'!$X$2:$X$20,B$13) | C18: =SUMIFS('Debt Database'!$K$2:$K$20,'Debt Database'!$B$2:$B$20,$A18,'Debt Database'!$X$2:$X$20,C$13) | D18: =SUMIFS('Debt Database'!$K$2:$K$20,'Debt Database'!$B$2:$B$20,$A18,'Debt Database'!$X$2:$X$20,D$13) | E18: =SUMIFS('Debt Database'!$K$2:$K$20,'Debt Database'!$B$2:$B$20,$A18,'Debt Database'!$X$2:$X$20,E$13) | F18: =SUMIFS('Debt Database'!$K$2:$K$20,'Debt Database'!$B$2:$B$20,$A18,'Debt Database'!$X$2:$X$20,F$13) | G18: =SUMIFS('Debt Database'!$K$2:$K$20,'Debt Database'!$B$2:$B$20,$A18,'Debt Database'!$X$2:$X$20,G$13) | H18: =SUMIFS('Debt Database'!$K$2:$K$20,'Debt Database'!$B$2:$B$20,$A18,'Debt Database'!$X$2:$X$20,H$13) | I18: =SUM(B18:H18)
A19: Other | B19: =SUMIFS('Debt Database'!$K$2:$K$20,'Debt Database'!$B$2:$B$20,$A19,'Debt Database'!$X$2:$X$20,B$13) | C19: =SUMIFS('Debt Database'!$K$2:$K$20,'Debt Database'!$B$2:$B$20,$A19,'Debt Database'!$X$2:$X$20,C$13) | D19: =SUMIFS('Debt Database'!$K$2:$K$20,'Debt Database'!$B$2:$B$20,$A19,'Debt Database'!$X$2:$X$20,D$13) | E19: =SUMIFS('Debt Database'!$K$2:$K$20,'Debt Database'!$B$2:$B$20,$A19,'Debt Database'!$X$2:$X$20,E$13) | F19: =SUMIFS('Debt Database'!$K$2:$K$20,'Debt Database'!$B$2:$B$20,$A19,'Debt Database'!$X$2:$X$20,F$13) | G19: =SUMIFS('Debt Database'!$K$2:$K$20,'Debt Database'!$B$2:$B$20,$A19,'Debt Database'!$X$2:$X$20,G$13) | H19: =SUMIFS('Debt Database'!$K$2:$K$20,'Debt Database'!$B$2:$B$20,$A19,'Debt Database'!$X$2:$X$20,H$13) | I19: =SUM(B19:H19)
A20: Total | B20: =SUM(B14:B19) | C20: =SUM(C14:C19) | D20: =SUM(D14:D19) | E20: =SUM(E14:E19) | F20: =SUM(F14:F19) | G20: =SUM(G14:G19) | H20: =SUM(H14:H19) | I20: =SUM(I14:I19)
A21: Of which bullet (notes + converts) | B21: =B15+B16 | C21: =C15+C16 | D21: =D15+D16 | E21: =E15+E16 | F21: =F15+F16 | G21: =G15+G16 | H21: =H15+H16 | I21: =I15+I16
A22: % of total | B22: =B20/$I$20 | C22: =C20/$I$20 | D22: =D20/$I$20 | E22: =E20/$I$20 | F22: =F20/$I$20 | G22: =G20/$I$20 | H22: =H20/$I$20
A23: Check: total vs Debt Databse | I23: =I20-'Debt Database'!K21
B46: Source: 10-Q Q2'26 Note 10; Debt Database. Amortizing debt (DDTLs, vendor financing) is shown at final maturity; actual balances will be lower by then. Bullets = senior notes + convertibles.

Sheet Scenarios
A1: Scenarios (downside cases)
A2: Set C4 to run the whole model under each case; column F (Active) feeds the model. Capex is held at base in all cases (largely committed GPU orders).
A4: Active scenario (1 = Base, 2 = Downside A, 3 = Downside B) | C4: 1
A5: Active scenario name | C5: =INDEX(C7:E7,$C$4)
A7: Driver | B7: Unit | C7: Base | D7: Downside A: GPU pricing | E7: Downside B: delays + pricing + rates | F7: Active | G7: Rationale
A8: 2H26 revenue: change vs guidance midpoint | B8: % chg | C8: 0 | D8: 0 | E8: -0.1 | F8: =INDEX(C8:E8,$C$4) | G8: Delivery delays (power, data-center readiness) push revenue out; CFO flagged a complex supply chain (Guidance tab, para 1)
A9: FY27 revenue: change vs exiting-2026 ARR | B9: % chg | C9: 0 | D9: 0 | E9: -0.2 | F9: =INDEX(C9:E9,$C$4) | G9: FY27 revenue below the exiting-2026 ARR run-rate: delays plus weaker pricing on re-contracting
A10: Adj. EBITDA margin (level) | B10: % | C10: ='PR_Q2-26'!D17/'PR_Q2-26'!D18 | D10: 0.45 | E10: 0.45 | F10: =INDEX(C10:E10,$C$4) | G10: Base = 1H26 actual. Downside: GPU rental prices fall as newer generations arrive; margin already down from 64% (FY24) to 57%
A11: SOFR shock on floating-rate debt | B11: bp | C11: 0 | D11: 0 | E11: 100 | F11: =INDEX(C11:E11,$C$4) | G11: Applied to floating-rate debt (Debt Database row 53, ~13.2bn); DDTL 3.0 is >=75% swapped, so slightly conservative
A12: New debt interest rate | B12: % | C12: 0.095 | D12: 0.11 | E12: 0.12 | F12: =INDEX(C12:E12,$C$4) | G12: Base: 2026 new notes 9.625-9.75%. Downside: credit spreads widen (DDTL 5.5 priced in a 'dislocated' week for credit)
A15: FY27E credit metrics | C15: Base | D15: Downside A | E15: Downside B | F15: Active (live) | G15: Note
A16: New financing required (2H26 + FY27) | C16: 44839.938 | D16: 48906.553 | E16: 51693.168 | F16: ='Funding Need'!D24 | G16: C:E = values pasted from column F for each case (switch C4 to 1/2/3); re-paste if any input changes - see check row 27
A17: FY27 Adj. EBITDA | C17: 10890.393 | D17: 8550 | E17: 6840 | F17: ='Funding Need'!C61 | G17: FY27 revenue held at exiting-2026 ARR (no growth) - conservative vs 37bn FY27 capex
A18: FY27 interest: existing debt + facility draws | C18: 3390.7154 | D18: 3390.7154 | E18: 3522.7754 | F18: ='Funding Need'!C8
A19: FY27 interest: new debt | C19: 2448.4858 | D19: 3116.9303 | E19: 3595.4468 | F19: ='Funding Need'!C25
A20: FY27 total interest | C20: 5839.2012 | D20: 6507.6457 | E20: 7118.2222 | F20: =F18+F19
A21: End-2027 debt | C21: 82022.938 | D21: 86089.553 | E21: 88876.168 | F21: ='Funding Need'!C38+'Funding Need'!B14+'Funding Need'!D24 | G21: Existing debt after maturities (FN C38) + facility draws (FN B14) + new financing (FN D24); new debt not repaid before 2028
A22: Less: minimum cash | C22: 2000 | D22: 2000 | E22: 2000 | F22: ='Funding Need'!B9 | G22: Model keeps a 2,000 minimum cash balance; all other cash is spent
A23: End-2027 net debt | C23: 80022.938 | D23: 84089.553 | E23: 86876.168 | F23: =F21-F22
A24: Debt / FY27 Adj. EBITDA | C24: 7.5316782 | D24: 10.068954 | E24: 12.993592 | F24: =F21/F17
A25: Net debt / FY27 Adj. EBITDA | C25: 7.3480301 | D25: 9.8350354 | E25: 12.701194 | F25: =F23/F17
A26: Adj. EBITDA / interest | C26: 1.8650485 | D26: 1.3138392 | E26: 0.96091409 | F26: =F17/F20 | G26: Below 1.0x = EBITDA does not cover interest
A27: Check: active column vs saved column for that case (should be 0) | F27: =ROUND(SUMPRODUCT(ABS(F16:F26-INDEX(C16:E26,0,$C$4))),3)

Sheet Assumptions Log
A1: Assumptions Log
A2: ="Every input that is not copied from a filing. Value (column D) links to the model. Impact = change vs base case (new financing "&TEXT('Funding Need'!D24,"#,##0")&"; FY27 debt / Adj. EBITDA "&TEXT(Scenarios!C24,"0.0")&"x; Adj. EBITDA / interest "&TEXT(Scenarios!C26,"0.00")&"x), one assumption at a time."
A4: # | B4: Area | C4: Assumption | D4: Value | E4: Unit | F4: Where used | G4: Source / basis | H4: Rationale | I4: Alternatives considered | J4: Impact if wrong
A5: 1 | B5: Scope | C5: Analysis date: use only information public on or before this date | D5: ='Debt Database'!B24 | E5: date | F5: All tabs; Debt Database B24 | G5: Q2'26 10-Q filed 8/12/2026 | H5: Day after the latest 10-Q: full Q2 financials plus subsequent events known by then; avoids look-ahead bias | I5: 7/1/2026 (before Q2 results) | J5: Including the Sep-26 converts or Q3 results would mix in information not available on the date
A6: 2 | B6: Debt | C6: DDTL 5.5 effective rate | D6: ='Debt Database'!B26 | E6: % | F6: Debt Database W20 | G6: 8-K: Term SOFR + 5.50% (0% floor) | H6: DDTL 5.0 (SOFR + 4.50%) shows a 9% effective rate in the 10-Q; 1.00% wider spread -> ~10% | I6: Coupon only (SOFR + 5.50%) | J6: +/-1pt = +/-$12m a year of interest; immaterial
A7: 3 | B7: Debt | C7: Debt measured at principal, not carrying value | D7: ='Debt Database'!K21 | E7: $mm | F7: Debt Database K21; Metrics; Funding Need | G7: 10-Q Note 10 Table 1 (principal by instrument) | H7: Principal is what must be repaid; unamortized discount ($483m) is an accounting item | I7: Carrying value (net of discount) | J7: Carrying value lowers debt by $0.5bn (~0.1x leverage)
A8: 4 | B8: Debt | C8: Interest on existing debt at 10-Q effective rates (weighted average) | D8: ='Debt Database'!W22 | E8: % | F8: Funding Need B40 | G8: 10-Q Note 10 Table 1 effective rates (whole %) | H8: Effective rates include discount amortization and fees: closest to reported interest expense | I8: Coupons; Q3'26 interest guidance ($860-940m) | J8: Rates are rounded to whole %: +/-0.5pt on $38bn = +/-$190m a year
A9: 5 | B9: Debt | C9: Floating-rate debt base for the SOFR shock | D9: ='Debt Database'!B53 | E9: $mm | F9: Funding Need row 42 | G9: Debt Database rate-type column | H9: Rows flagged Floating; hedges not netted (conservative) | I9: Net of DDTL 3.0 swaps (>=75%), add DDTL 4.0 floating tranche | J9: +100bp = +$132m a year; netting DDTL 3.0 swaps cuts it by ~$17m
A10: 6 | B10: Funding | C10: Capex on the company's definition, not cash capex | D10: ='Funding Need'!B32 | E10: $mm (1H26) | F10: Funding Need rows 29-33 | G10: Earnings Presentation slide 16 (definition and calculation) | H10: Guidance is given on this basis, so 2H26 = guidance - 1H26 is like for like | I10: Cash capex (1H26 $14.1bn, cash flow statement) | J10: Company basis exceeded cash capex by $2.0bn in 1H26 (finance leases, CIP timing): near-term need may be overstated
A11: 7 | B11: Funding | C11: FY26 capex at guidance midpoint ($35-39bn) | D11: ='Funding Need'!B31 | E11: $mm | F11: Funding Need B31 -> 2H26 capex B33 | G11: Outlook Presentation (Guidance tab E9) | H11: Midpoint of the company's own range | I11: High end $39bn | J11: High end: +$2.3bn new financing; FY27 leverage 7.7x
A12: 8 | B12: Funding | C12: FY27 capex flat at FY26 midpoint | D12: ='Funding Need'!C33 | E12: $mm | F12: Funding Need C33 | G12: No FY27 guidance; no public consensus found dated before 8/13 | H12: Neutral: keeps capacity build at the 2026 pace | I12: Growth with power targets (>3 GW end-2027); consensus | J12: Each +$5bn: +$5.2bn new financing; leverage 8.0x
A13: 9 | B13: Funding | C13: 2H26 revenue = FY26 guidance midpoint less 1H26 actual | D13: ='Funding Need'!B57 | E13: $mm | F13: Funding Need B57 | G13: Outlook Presentation ($12.4-13.2bn); Q2'26 press release | H13: Company guidance, consistent with the capex basis | I13: Low end $12.4bn | J13: -10%: +$0.5bn new financing
A14: 10 | B14: Funding | C14: FY27 revenue held at exiting-2026 ARR midpoint (no growth) | D14: ='Funding Need'!C57 | E14: $mm | F14: Funding Need C57 | G14: Outlook Presentation ($18.5-19.5bn exiting ARR) | H14: Only company figure for the 2027 run-rate; conservative | I14: Grow with active power (~$25bn at 2.4 GW average) | J14: At $25bn: -$3.6bn new financing; leverage 5.5x; coverage 2.53x (base leverage is overstated)
A15: 11 | B15: Funding | C15: Adj. EBITDA margin = 1H26 actual, flat in FY27 | D15: =Scenarios!C10 | E15: % | F15: Scenarios C10 -> Funding Need row 60 | G15: Q2'26 press release (2,667 / 4,653) | H15: Latest actual; margin fell from 64% (FY24) to 57% | I15: Q2'26 alone (59%); CFO guides to expanding margins | J15: -5pt: +$1.5bn new financing; coverage 1.68x
A16: 12 | B16: Funding | C16: Cash taxes and working capital = 0 (customer prepayments ignored) | D16: ='Funding Need'!B62 | E16: $mm | F16: Funding Need row 62 | G16: Judgment | H16: Loss-making, so little cash tax; prepayments are lumpy and not contracted to recur | I16: 1H26 pace: ~$1.8bn working-capital inflow per half | J16: At the 1H26 pace: -$5.8bn new financing (largest single upside to base)
A17: 13 | B17: Funding | C17: Minimum cash balance | D17: ='Funding Need'!B9 | E17: $mm | F17: Funding Need B9 | G17: Judgment | H17: ~1 quarter of cash operating costs (2H26 revenue x (1 - margin) / 2 = ~$1.7bn), rounded up | I17: One quarter of debt service (~$3bn) | J17: +$1bn: +$1.1bn new financing
A18: 14 | B18: Funding | C18: Restricted cash excluded from sources | D18: ='10Q_BS'!B9+'10Q_BS'!B14 | E18: $mm | F18: Funding Need B13 | G18: 10-Q balance sheet | H18: Held in reserve accounts of financing SPVs; not available for general use | I18: Include it (the CFO's '$6.9bn' liquidity does) | J18: Including it: -$1.4bn new financing
A19: 15 | B19: Funding | C19: Undrawn committed facilities fully used for 2H26 capex | D19: ='Funding Need'!B14 | E19: $mm | F19: Funding Need B14 | G19: Debt Database (undrawn at 8/13) | H19: DDTL draws can only fund capex on financed contracts; assumed to match planned capex | I19: Partial use (draw periods lapse, e.g. DDTL 5.0 on 9/30/2026) | J19: Unused capacity is replaced by new debt at 9.5%
A20: 16 | B20: Funding | C20: Existing-debt interest on average balance; repayments spread evenly | D20: ='Funding Need'!B40 | E20: % | F20: Funding Need rows 36-44 | G20: 10-Q maturity schedule (Table 3) | H20: Standard average-balance convention | I20: Opening balance (no credit for repayments) | J20: Opening balance: +$0.4bn interest over 2H26-FY27
A21: 17 | B21: Funding | C21: Facility draws: drawn evenly in 2H26, at the weighted average rate | D21: ='Funding Need'!C43 | E21: $mm (FY27) | F21: Funding Need row 43 | G21: Debt Database | H21: Undrawn capacity becomes debt once used | I21: Facility-specific rates (~7.8% weighted) | J21: ~-$60m a year at 7.8%; immaterial
A22: 18 | B22: Funding | C22: New debt interest rate | D22: =Scenarios!C12 | E22: % | F22: Scenarios C12 -> Funding Need B21 | G22: 2026 issues: 2031 notes 9.75%, 2032 notes 9.625% (10Q_Debt Table 2); DDTL 5.0 ~9%; DDTL 5.5 ~10% | H22: Blend of recent secured and unsecured pricing | I22: Convert-heavy mix (~2% coupons) | J22: +1pt: +$0.3bn new financing; coverage 1.78x
A23: 19 | B23: Funding | C23: New debt drawn evenly; bullet, not repaid before 2028 | D23: ='Funding Need'!B23 | E23: factor | F23: Funding Need B23:C23 | G23: Judgment | H23: Borrowing follows capex through the period | I23: Front-loaded borrowing | J23: Front-loading raises 2H26 interest; small
A24: 20 | B24: Maturity | C24: DDTL 5.5 placed at final maturity (Sep 2031) | D24: =Maturity!G7 | E24: $mm | F24: Maturity row 7 | G24: 8-K (amortization schedule not disclosed) | H24: No schedule disclosed | I24: Amortize like DDTL 5.0 | J24: Moves up to $1.2bn from 'Thereafter' into 2027-31
A25: 21 | B25: Metrics | C25: LTM = FY25 + 1H26 - 1H25; company Adj. EBITDA as earnings measure | D25: =Metrics!E6 | E25: $mm | F25: Metrics column E | G25: Q4'25 and Q2'26 press releases | H25: Latest four quarters; the non-GAAP measure lenders and the company use | I25: GAAP EBITDA; FY25 alone | J25: Adj. EBITDA adds back ~$0.6bn of LTM stock-based compensation
A26: 22 | B26: Metrics | C26: Run-rate = Q2'26 x 4 | D26: =Metrics!G6 | E26: $mm | F26: Metrics column G | G26: Q2'26 press release | H26: Captures growth that LTM lags | I26: Q3'26 guidance annualized | J26: Understates if June's 300 MW of new capacity ramps; overstates if Q2 had one-offs
A27: 23 | B27: Metrics | C27: Principal due in 12 months = 10-Q current portion of debt | D27: =Metrics!E31 | E27: $mm | F27: Metrics E31 | G27: 10-Q Note 10 (current portion, carrying value) | H27: Matches the 12-month window exactly | I27: Table 3: 2H26 + half of 2027 ($7,505m) | J27: ~$8m difference; immaterial
A28: 24 | B28: Scenarios | C28: Downside drivers (margin 45%, revenue -10%/-20%, SOFR +100bp, new debt 11-12%); capex held at plan in all cases | D28: =Scenarios!D10 | E28: % (case A/B margin) | F28: Scenarios tab | G28: Judgment (rationale in Scenarios column G) | H28: Tests pricing, delays and rates alone and combined | I28: Cut capex in the downside (management lever) | J28: Case B: coverage 0.96x; holding capex makes the downside harsher than if management cut spending
